Workbook

Sheet Дилеры_Август
A1: __EMPTY | B1: Время закрытия | C1: Deal_ID | D1: Идентификатор компании | E1: Название стадии | F1: Contact_ID | G1: client_id | H1: Название компании | I1: ИНН | J1: КВ. ИИ | K1: отчеты | L1: комментарий | N1: Цена | O1: КВ. Авто | P1: Номер ДКП | Q1: Дата ДКП | R1: brand | S1: model | T1: TYPE | U1: VIN | V1: Цена | W1: КВ. Авто | X1: Название товара | Y1: CITY | Z1: YEAR | AA1: Error | AB1: Ссылка на сделку
A2: 1391 | B2: 46238 | C2: 507548 | D2: 113190 | E2: Закрыто и реализованно | F2: 489446 | G2: 4733196 | H2: Online ГК Башавтоком, ООО "СТРОЙМОСТИНВЕСТ" | I2: 245013286 | J2: 28600 | K2: да | L2: ии не проверил | N2: 1430000 | O2: 28600 | P2: СМ000002442 | Q2: 46238 | R2: Lada (ВАЗ) | S2: Niva | T2: Новое | U2: XTA212310T0985466 | V2: 1430000 | W2: 28600 | X2: Lada (ВАЗ) Niva XTA212310T0985466 | Y2: Стерлитамак | Z2: 2026 | AA2: FALSE | AB2: <a href="https://sberauto.bitrix24.ru/crm/deal/details/507548/"target="_blank">Ссылка</a>
A3: 1579 | B3: 46238 | C3: 503526 | D3: 1956 | E3: Закрыто и реализованно | F3: 489446 | G3: 4733196 | H3: ГК Башавтоком, ООО "СТРОЙМОСТИНВЕСТ" | I3: 245013286 | L3: дубль сделки. | N3: 1430000 | O3: 28600 | P3: СМ000002442 | Q3: 46238 | R3: Lada (ВАЗ) | S3: Niva | T3: Новое | U3: XTA212310T0985466 | V3: 1430000 | W3: 28600 | X3: Lada (ВАЗ) Niva XTA212310T0985466 | Y3: Стерлитамак | Z3: 2026 | AA3: FALSE | AB3: <a href="https://sberauto.bitrix24.ru/crm/deal/details/503526/"target="_blank">Ссылка</a>
A4: 33 | B4: 46265 | C4: 535350 | D4: 113078 | E4: Закрыто и реализованно | F4: 510280 | G4: 4953612 | H4: ООО "МС МОТОРС ЗУБОВО" ONLINE | I4: 245961925 | J4: 49200 | K4: да | L4: ии не проверил | N4: 2460000 | O4: 49200 | P4: 26/08-46/AM | Q4: 46261 | R4: Jetour | S4: X70Plus | T4: Новое | U4: EC37LUSM6TC006527 | V4: 2460000 | W4: 49200 | X4: Jetour X70Plus EC37LUSM6TC006527 | Y4: Уфа | Z4: 2026 | AA4: FALSE | AB4: <a href="https://sberauto.bitrix24.ru/crm/deal/details/535350/"target="_blank">Ссылка</a>
A5: 1277 | B5: 46241 | C5: 509914 | D5: 113078 | E5: Закрыто и реализованно | F5: 494376 | G5: 5010914 | H5: ООО "МС МОТОРС ЗУБОВО" ONLINE | I5: 245961925 | J5: 48000 | K5: да | L5: ии не проверил | N5: 2400000 | O5: 48000 | P5: 26/08-07/AM | Q5: 46239 | R5: JETOUR | S5: DASHING | T5: Новое | U5: EC3DLUFD7TC013063 | V5: 2400000 | W5: 48000 | X5: JETOUR DASHING EC3DLUFD7TC013063 | Y5: Уфа | Z5: 2026 | AA5: FALSE | AB5: <a href="https://sberauto.bitrix24.ru/crm/deal/details/509914/"target="_blank">Ссылка</a>
A6: 1063 | B6: 46250 | C6: 514374 | D6: 76632 | E6: Закрыто и реализованно | F6: 497630 | G6: 5047174 | H6: ONLINE Динамика (ООО "ДИНАМИКА") | I6: 263009243 | J6: 32385 | K6: да | L6: ии не проверил | N6: 2159000 | O6: 32385 | P6: ЗА000004866 | Q6: 46246 | R6: JETOUR | S6: DASHING | T6: Новое | U6: EC3DCUFD5TC016057 | V6: 2159000 | W6: 32385 | X6: JETOUR DASHING EC3DCUFD5TC016057 | Y6: Архангельск | Z6: 2026 | AA6: FALSE | AB6: <a href="https://sberauto.bitrix24.ru/crm/deal/details/514374/"target="_blank">Ссылка</a>
A7: 480 | B7: 46260 | C7: 528212 | D7: 113516 | E7: Закрыто и реализованно | F7: 505728 | G7: 1354944 | H7: ООО "УРАЛ-МОТОРС" ONLINE | I7: 268068757 | J7: 74000 | K7: да | N7: 3700000 | O7: 74000 | P7: 2000 | Q7: 46259 | R7: Gac | S7: GS4 | T7: Новое | U7: LMGAE3G80T1004612 | V7: 3700000 | W7: 74000 | X7: Gac GS4 LMGAE3G80T1004612 | Y7: Стерлитамак | Z7: 2026 | AA7: FALSE | AB7: <a href="https://sberauto.bitrix24.ru/crm/deal/details/528212/"target="_blank">Ссылка</a>
A8: 1568 | B8: 46238 | C8: 505868 | D8: 113146 | E8: Закрыто и реализованно | F8: 491196 | G8: 4967624 | H8: Online ДАКТОР УФА СЕЛЬСКАЯ | I8: 276971419 | K8: да | L8: ии не проверил | N8: 2020900 | O8: 40418 | P8: УС000000434 | Q8: 46237 | R8: JETOUR | S8: DASHING | T8: Новое | U8: EC3DLUFD1TC012961 | V8: 2020900 | W8: 40418 | X8: JETOUR DASHING EC3DLUFD1TC012961 | Y8: Уфа | Z8: 2026 | AA8: FALSE | AB8: <a href="https://sberauto.bitrix24.ru/crm/deal/details/505868/"target="_blank">Ссылка</a>
A9: 180 | B9: 46264 | C9: 534038 | D9: 79732 | E9: Закрыто и реализованно | F9: 503164 | G9: 5093745 | H9: ONLINE Башавтоком (ООО "БАШАВТОКОМ-В") | I9: 278105341 | K9: да | L9: ии не проверил | N9: 1225000 | O9: 18375 | P9: B0000002711 | Q9: 46262 | R9: LADA | S9: GRANTA | T9: Новое | U9: ХТА219440V0324759 | V9: 1225000 | W9: 18375 | X9: Lada Granta ХТА219440V0324759 | Y9: Стерлитамак | Z9: 2026 | AA9: FALSE | AB9: <a href="https://sberauto.bitrix24.ru/crm/deal/details/534038/"target="_blank">Ссылка</a>
A10: 182 | B10: 46264 | C10: 534010 | D10: 79732 | E10: Закрыто и реализованно | F10: 503386 | G10: 5094393 | H10: ONLINE Башавтоком (ООО "БАШАВТОКОМ-В") | I10: 278105341 | K10: да | L10: ии не проверил | N10: 1121000 | O10: 16815 | P10: B0000002793 | Q10: 46262 | R10: LADA | S10: GRANTA | T10: Новое | U10: ХТА219040T1268071 | V10: 1121000 | W10: 16815 | X10: Lada Granta ХТА219040T1268071 | Y10: Стерлитамак | Z10: 2026 | AA10: FALSE | AB10: <a href="https://sberauto.bitrix24.ru/crm/deal/details/534010/"target="_blank">Ссылка</a>
A11: 372 | B11: 46260 | C11: 529958 | D11: 79732 | E11: Закрыто и реализованно | F11: 506378 | G11: 5120595 | H11: ONLINE Башавтоком (ООО "БАШАВТОКОМ-В") | I11: 278105341 | K11: да | L11: ии не проверил | N11: 1088000 | O11: 16320 | P11: B0000002772 | Q11: 46260 | R11: LADA | S11: GRANTA | T11: Новое | U11: XTA219040V1276059 | V11: 1088000 | W11: 16320 | X11: LADA GRANTA XTA219040V1276059 | Y11: Стерлитамак | Z11: 2026 | AA11: FALSE | AB11: <a href="https://sberauto.bitrix24.ru/crm/deal/details/529958/"target="_blank">Ссылка</a>
A12: 392 | B12: 46260 | C12: 529690 | D12: 79732 | E12: Закрыто и реализованно | F12: 505776 | G12: 5114557 | H12: ONLINE Башавтоком (ООО "БАШАВТОКОМ-В") | I12: 278105341 | K12: да | L12: ии не проверил | N12: 1654000 | O12: 24810 | P12: B0000002754 | Q12: 46259 | R12: LADA | S12: GRANTA | T12: Новое | U12: ХТА219040V1276057 | V12: 1654000 | W12: 24810 | X12: LADA GRANTA ХТА219040V1276057 | Y12: Стерлитамак | Z12: 2026 | AA12: FALSE | AB12: <a href="https://sberauto.bitrix24.ru/crm/deal/details/529690/"target="_blank">Ссылка</a>
A13: 494 | B13: 46258 | C13: 528042 | D13: 79732 | E13: Закрыто и реализованно | F13: 504390 | G13: 5104689 | H13: ONLINE Башавтоком (ООО "БАШАВТОКОМ-В") | I13: 278105341 | K13: да | L13: ии не проверил | N13: 1226000 | O13: 18390 | P13: B0000002734 | Q13: 46257 | R13: Lada | S13: Granta Cross | T13: Новое | U13: ХТА219470V0324758 | V13: 1226000 | W13: 18390 | X13: Lada Granta Cross ХТА219470V0324758 | Y13: Стерлитамак | Z13: 2026 | AA13: FALSE | AB13: <a href="https://sberauto.bitrix24.ru/crm/deal/details/528042/"target="_blank">Ссылка</a>
A14: 629 | B14: 46255 | C14: 526118 | D14: 79732 | E14: Закрыто и реализованно | F14: 503728 | G14: 5098167 | H14: ONLINE Башавтоком (ООО "БАШАВТОКОМ-В") | I14: 278105341 | K14: да | L14: ии не проверил | N14: 1189000 | O14: 17835 | P14: B0000002707 | Q14: 46255 | R14: LADA | S14: GRANTA | T14: Новое | U14: ХТА219440V0323249 | V14: 1189000 | W14: 17835 | X14: LADA GRANTA ХТА219440V0323249 | Y14: Стерлитамак | Z14: 2026 | AA14: FALSE | AB14: <a href="https://sberauto.bitrix24.ru/crm/deal/details/526118/"target="_blank">Ссылка</a>
A15: 713 | B15: 46255 | C15: 524852 | D15: 79732 | E15: Закрыто и реализованно | F15: 502676 | G15: 5088606 | H15: ONLINE Башавтоком (ООО "БАШАВТОКОМ-В") | I15: 278105341 | K15: да | L15: ии не проверил | N15: 1198000 | O15: 17970 | P15: B0000002695 | Q15: 46254 | R15: LADA | S15: GRANTA | T15: Новое | U15: XTA219470V0323264 | V15: 1198000 | W15: 17970 | X15: LADA Granta XTA219470V0323264 | Y15: Стерлитамак | Z15: 2026 | AA15: FALSE | AB15: <a href="https://sberauto.bitrix24.ru/crm/deal/details/524852/"target="_blank">Ссылка</a>
A16: 803 | B16: 46252 | C16: 523192 | D16: 79732 | E16: Закрыто и реализованно | F16: 501182 | G16: 5077481 | H16: ONLINE Башавтоком (ООО "БАШАВТОКОМ-В") | I16: 278105341 | K16: да | L16: ии не проверил | N16: 1096000 | O16: 16440 | P16: B0000002659 | Q16: 46252 | R16: LADA | S16: GRANTA | T16: Новое | U16: ХТА219040V1275881 | V16: 1096000 | W16: 16440 | X16: LADA GRANTA ХТА219040V1275881 | Y16: Стерлитамак | Z16: 2026 | AA16: FALSE | AB16: <a href="https://sberauto.bitrix24.ru/crm/deal/details/523192/"target="_blank">Ссылка</a>
A17: 875 | B17: 46250 | C17: 518180 | D17: 79732 | E17: Закрыто и реализованно | F17: 500418 | G17: 5070713 | H17: ONLINE Башавтоком (ООО "БАШАВТОКОМ-В") | I17: 278105341 | K17: да | L17: ии не проверил | N17: 1832000 | O17: 27480 | P17: B0000002633 | Q17: 46250 | R17: LADA | S17: Vesta | T17: Новое | U17: XTAGFL110V1060519 | V17: 1832000 | W17: 27480 | X17: Lada Vesta XTAGFL110V1060519 | Y17: Уфа | Z17: 2026 | AA17: FALSE | AB17: <a href="https://sberauto.bitrix24.ru/crm/deal/details/518180/"target="_blank">Ссылка</a>
A18: 884 | B18: 46250 | C18: 518072 | D18: 79732 | E18: Закрыто и реализованно | F18: 497164 | G18: 5041658 | H18: ONLINE Башавтоком (ООО "БАШАВТОКОМ-В") | I18: 278105341 | K18: да | L18: ии не проверил | N18: 1789000 | O18: 26835 | P18: В0000002539 | Q18: 46248 | R18: LADA | S18: Niva Travel | T18: Новое | U18: XTA212310T1000782 | V18: 1789000 | W18: 26835 | X18: LADA Niva Travel XTA212310T1000782 | Y18: Стерлитамак | Z18: 2026 | AA18: FALSE | AB18: <a href="https://sberauto.bitrix24.ru/crm/deal/details/518072/"target="_blank">Ссылка</a>
A19: 936 | B19: 46249 | C19: 517190 | D19: 79732 | E19: Закрыто и реализованно | F19: 499130 | G19: 5059112 | H19: ONLINE Башавтоком (ООО "БАШАВТОКОМ-В") | I19: 278105341 | K19: да | L19: ии не проверил | N19: 1810000 | O19: 27150 | P19: B0000002585 | Q19: 46248 | R19: LADA | S19: Niva | T19: Новое | U19: XTA212310V1005472 | V19: 1810000 | W19: 27150 | X19: Lada Niva XTA212310V1005472 | Y19: Стерлитамак | Z19: 2026 | AA19: FALSE | AB19: <a href="https://sberauto.bitrix24.ru/crm/deal/details/517190/"target="_blank">Ссылка</a>
... A23: 892 | B23: 46252 | C23: 517968 | D23: 82164 | E23: Закрыто и реализованно | F23: 500490 | G23: 2718950 | H23: ONLINE CHERY Динамика (ООО "ДИНАМИКА АРХАНГЕЛЬСК РР") | I23: 1101096766 | K23: да | L23: ии не проверил | N23: 2100000 | O23: 21000 | P23: ЗА000004994 | Q23: 46251 | R23: JETOUR | S23: DASHING | T23: Новое | U23: EC3DCUFD8TC010687 | V23: 2100000 | W23: 21000 | X23: Jetour Dashing EC3DCUFD8TC010687 | Y23: Архангельск | Z23: 2026 | AA23: FALSE | AB23: <a href="https://sberauto.bitrix24.ru/crm/deal/details/517968/"target="_blank">Ссылка</a>
A24: 262 | B24: 46262 | C24: 532232 | D24: 113584 | E24: Закрыто и реализованно | F24: 508644 | G24: 5142873 | H24: АЛЕКСМОТОРС ONLINE | I24: 1101126185 | J24: 75000 | K24: да | N24: 3750000 | O24: 75000 | P24: ДФ 0079/2026 | Q24: 46262 | R24: JETOUR | S24: Т1 | T24: Новое | U24: LVTDD24B5TDB86498 | V24: 3750000 | W24: 75000 | X24: Jetour T1 LVTDD24B5TDB86498 | Y24: Сыктывкар | Z24: 2026 | AA24: FALSE | AB24: <a href="https://sberauto.bitrix24.ru/crm/deal/details/532232/"target="_blank">Ссылка</a>
A25: 11 | B25: 46265 | C25: 535452 | D25: 112880 | E25: Закрыто и реализованно | F25: 511438 | G25: 5166407 | H25: Online ООО "ЛЕОН" | I25: 1207901941 | J25: 51000 | K25: да | N25: 2550000 | O25: 51000 | P25: ДТ-72 | Q25: 46265 | R25: Soueast | S25: S06 | T25: Новое | U25: EC3DCUGA5TC000896 | V25: 2550000 | W25: 51000 | X25: Soueast S06 EC3DCUGA5TC000896 | Y25: РЕСПУБЛИКА МАРИЙ ЭЛ | Z25: 2026 | AA25: FALSE | AB25: <a href="https://sberauto.bitrix24.ru/crm/deal/details/535452/"target="_blank">Ссылка</a>
A26: 181 | B26: 46264 | C26: 534018 | D26: 112880 | E26: Закрыто и реализованно | F26: 501946 | G26: 4893504 | H26: Online ООО "ЛЕОН" | I26: 1207901941 | J26: 73400 | K26: да | N26: 3670000 | O26: 73400 | P26: ДТ-61 | Q26: 46263 | R26: JETOUR | S26: Т1 | T26: Новое | U26: LVTDD24B4TDB99632 | V26: 3670000 | W26: 73400 | X26: JETOUR T1 LVTDD24B4TDB99632 | Y26: Медведево | Z26: 2026 | AA26: FALSE | AB26: <a href="https://sberauto.bitrix24.ru/crm/deal/details/534018/"target="_blank">Ссылка</a>
A27: 1525 | B27: 46237 | C27: 506246 | D27: 112880 | E27: Закрыто и реализованно | F27: 489892 | G27: 4970808 | H27: Online ООО "ЛЕОН" | I27: 1207901941 | J27: 42600 | K27: да | N27: 2130000 | O27: 42600 | P27: ДТ-46 | Q27: 46234 | R27: JETOUR | S27: X70 PLUS | T27: Новое | U27: EC37CUSM5TC005868 | V27: 2130000 | W27: 42600 | X27: JETOUR X70 PLUS EC37CUSM5TC005868 | Y27: Медведево | Z27: 2026 | AA27: FALSE | AB27: <a href="https://sberauto.bitrix24.ru/crm/deal/details/506246/"target="_blank">Ссылка</a>
A28: 1528 | B28: 46237 | C28: 506206 | D28: 112880 | E28: Закрыто и реализованно | F28: 491448 | G28: 4708919 | H28: Online ООО "ЛЕОН" | I28: 1207901941 | J28: 45400 | K28: да | N28: 2270000 | O28: 45400 | P28: ДТ-45 | Q28: 46234 | R28: JETOUR | S28: X70 PLUS | T28: Новое | U28: EC37LUSM6TC006575 | V28: 2270000 | W28: 45400 | X28: JETOUR X70 PLUS EC37LUSM6TC006575 | Y28: МЕДВЕДЕВО | Z28: 2026 | AA28: FALSE | AB28: <a href="https://sberauto.bitrix24.ru/crm/deal/details/506206/"target="_blank">Ссылка</a>
A29: 1594 | B29: 46238 | C29: 502336 | D29: 111882 | E29: Закрыто и реализованно | F29: 488506 | G29: 4957664 | H29: ООО "КМ-АВТО САРАНСК-2" ONLINE | I29: 1300005883 | J29: 57000 | K29: да | N29: 2850000 | O29: 57000 | P29: М000000068 | Q29: 46235 | R29: Solaris | S29: KRX | T29: Новое | U29: Z94C351BBSR196070 | V29: 2850000 | W29: 57000 | X29: Solaris KRX Z94C351BBSR196070 | Y29: Саранск | Z29: 2026 | AA29: FALSE | AB29: <a href="https://sberauto.bitrix24.ru/crm/deal/details/502336/"target="_blank">Ссылка</a>
A30: 1673 | B30: 46246 | C30: 483622 | D30: 111882 | E30: Закрыто и реализованно | F30: 475000 | G30: 4830365 | H30: ООО "КМ-АВТО САРАНСК-2" ONLINE | I30: 1300005883 | J30: 51000 | K30: да | N30: 2550000 | O30: 51000 | P30: М000000061 | Q30: 46212 | R30: Solaris | S30: KRX | T30: Новое | U30: Z94C251BBSR200339 | V30: 2550000 | W30: 51000 | X30: Solaris KRX Z94C251BBSR200339 | Y30: Саранск | Z30: 2025 | AA30: FALSE | AB30: <a href="https://sberauto.bitrix24.ru/crm/deal/details/483622/"target="_blank">Ссылка</a>
A31: 147 | B31: 46264 | C31: 534388 | D31: 112710 | E31: Закрыто и реализованно | F31: 473224 | G31: 1479681 | H31: ООО "АРМАДА-АВТО" online | I31: 1615009225 | J31: 49200 | K31: да | N31: 2460000 | O31: 49200 | P31: AA00000983 | Q31: 46263 | R31: JETOUR | S31: X70+ | T31: Новое | U31: EC37LUSM9TC007350 | V31: 2460000 | W31: 49200 | X31: JETOUR X70+ EC37LUSM9TC007350 | Y31: Нижнекамск | Z31: 2026 | AA31: FALSE | AB31: <a href="https://sberauto.bitrix24.ru/crm/deal/details/534388/"target="_blank">Ссылка</a>
A32: 1337 | B32: 46239 | C32: 508702 | D32: 112710 | E32: Закрыто и реализованно | F32: 261898 | G32: 2908721 | H32: ООО "АРМАДА-АВТО" online | I32: 1615009225 | J32: 57456 | K32: да | N32: 2872800 | O32: 57456 | P32: АА00000857 | Q32: 46239 | R32: SOLARIS | S32: HC | T32: Новое | U32: Z94PF815BSR065403 | V32: 2872800 | W32: 57456 | X32: Solaris HC Z94PF815BSR065403 | Y32: Нижнекамск | Z32: 2025 | AA32: FALSE | AB32: <a href="https://sberauto.bitrix24.ru/crm/deal/details/508702/"target="_blank">Ссылка</a>
A33: 1654 | B33: 46238 | C33: 490494 | D33: 108228 | E33: Закрыто и реализованно | F33: 479820 | G33: 4878511 | H33: ONLINE ГК Диалог \ ООО Диалог Авто | I33: 1644062657 | J33: 42600 | K33: да | N33: 2130000 | O33: 42600 | P33: 26/07/17-02 | Q33: 46220 | R33: Jetour | S33: X70 + | T33: Новое | U33: EC37CUSM4SC004659 | V33: 2130000 | W33: 42600 | X33: Jetour X70 + EC37CUSM4SC004659 | Y33: Казань | Z33: 2026 | AA33: FALSE | AB33: <a href="https://sberauto.bitrix24.ru/crm/deal/details/490494/"target="_blank">Ссылка</a>
A34: 1266 | B34: 46248 | C34: 510012 | D34: 107326 | E34: Закрыто и реализованно | F34: 494476 | G34: 4777908 | H34: ONLINE ООО "ДИАЛОГ АВТО" | I34: 1644062657 | J34: 40000 | K34: да | N34: 2000000 | O34: 40000 | P34: 26/08/07-01 | Q34: 46241 | R34: Jetour | S34: Dashing | T34: Новое | U34: EC3DCUFD8TC014626 | V34: 2000000 | W34: 40000 | X34: Jetour Dashing EC3DCUFD8TC014626 | Y34: Казань | Z34: 2026 | AA34: FALSE | AB34: <a href="https://sberauto.bitrix24.ru/crm/deal/details/510012/"target="_blank">Ссылка</a>
A35: 20 | B35: 46265 | C35: 535394 | D35: 107326 | E35: Закрыто и реализованно | F35: 511386 | G35: 5094107 | H35: ONLINE ООО "ДИАЛОГ АВТО" | I35: 1644062657 | J35: 10800 | K35: да | N35: 540000 | O35: 10800 | P35: 26/08/31-05 | Q35: 46265 | R35: Mini | S35: One | T35: Б/У | U35: WMWME31090TU04249 | V35: 540000 | W35: 10800 | X35: Mini One WMWME31090TU04249 | Y35: Альметьевск | Z35: 2007 | AA35: FALSE | AB35: <a href="https://sberauto.bitrix24.ru/crm/deal/details/535394/"target="_blank">Ссылка</a>
... A69: 1518 | B69: 46237 | C69: 506282 | D69: 102862 | E69: Закрыто и реализованно | F69: 491510 | G69: 4979253 | H69: ONLINE ДИАЛОГ А | I69: 1649021206 | J69: 39400 | K69: да | N69: 1970000 | O69: 39400 | P69: 26/08/01-01 | Q69: 46235 | R69: JETOUR | S69: DASHING | T69: Новое | U69: EC3DCUFDXTC014546 | V69: 1970000 | W69: 39400 | X69: JETOUR DASHING EC3DCUFDXTC014546 | Y69: Набережные Челны | Z69: 2026 | AA69: FALSE | AB69: <a href="https://sberauto.bitrix24.ru/crm/deal/details/506282/"target="_blank">Ссылка</a>
A70: 406 | B70: 46259 | C70: 529510 | D70: 102862 | E70: Закрыто и реализованно | F70: 501906 | G70: 5074421 | H70: ONLINE ДИАЛОГ А | I70: 1649021206 | J70: 52260 | K70: да | L70: лид | N70: 2613000 | O70: 52260 | P70: 26/08/19-49 | Q70: 46253 | R70: TENET | S70: Т7 | T70: Новое | U70: EDXFB32B6TE091320 | V70: 2613000 | W70: 52260 | X70: TENET Т7 EDXFB32B6TE091320 | Y70: Казань | Z70: 2026 | AA70: FALSE | AB70: <a href="https://sberauto.bitrix24.ru/crm/deal/details/529510/"target="_blank">Ссылка</a>
A71: 527 | B71: 46263 | C71: 527450 | D71: 97080 | E71: Закрыто и реализованно | F71: 505138 | G71: 2778792 | H71: ONLINE Автодин (ООО "АВТОДИН-КАМА") | I71: 1650129620 | J71: 90000 | K71: да | N71: 4500000 | O71: 90000 | P71: 3472 | Q71: 46263 | R71: Geely | S71: Monjaro | T71: Новое | U71: LB37852D0TS064011 | V71: 4500000 | W71: 90000 | X71: Geely Monjaro LB37852D0TS064011 | Y71: Москва | Z71: 2026 | AA71: FALSE | AB71: <a href="https://sberauto.bitrix24.ru/crm/deal/details/527450/"target="_blank">Ссылка</a>
A72: 1038 | B72: 46246 | C72: 514734 | D72: 97080 | E72: Закрыто и реализованно | F72: 497900 | G72: 4371154 | H72: ONLINE Автодин (ООО "АВТОДИН-КАМА") | I72: 1650129620 | J72: 55100 | K72: да | N72: 2755000 | O72: 55100 | P72: 3332 | Q72: 46242 | R72: BELGEE | S72: X50+ | T72: Новое | U72: Y4K8622Z9TB933027 | V72: 2755000 | W72: 55100 | X72: BELGEE X50+ Y4K8622Z9TB933027 | Y72: Москва | Z72: 2026 | AA72: FALSE | AB72: <a href="https://sberauto.bitrix24.ru/crm/deal/details/514734/"target="_blank">Ссылка</a>
A73: 484 | B73: 46258 | C73: 528186 | D73: 108224 | E73: Закрыто и реализованно | F73: 500632 | G73: 3481983 | H73: Online ГК Диалог \ ООО "Управляющая компания Диалог" | I73: 1650207558 | J73: 92600 | K73: да | N73: 4630000 | O73: 92600 | P73: 26/08/21-03 | Q73: 46255 | R73: Gac | S73: GS8 | T73: Новое | U73: LMGJU3G89T1061877 | V73: 4630000 | W73: 92600 | X73: Gac GS8 LMGJU3G89T1061877 | Y73: Набережные Челны | Z73: 2026 | AA73: FALSE | AB73: <a href="https://sberauto.bitrix24.ru/crm/deal/details/528186/"target="_blank">Ссылка</a>
A74: 1206 | B74: 46244 | C74: 510974 | D74: 108224 | E74: Закрыто и реализованно | F74: 495240 | G74: 5024076 | H74: Online ГК Диалог \ ООО "Управляющая компания Диалог" | I74: 1650207558 | J74: 112000 | K74: да | N74: 5600000 | O74: 112000 | P74: 26/08/08-03 | Q74: 46242 | R74: GAC | S74: S7 | T74: Новое | U74: LMGNC3S82T1001158 | V74: 5600000 | W74: 112000 | X74: GAC S7 LMGNC3S82T1001158 | Y74: Казань | Z74: 2026 | AA74: FALSE | AB74: <a href="https://sberauto.bitrix24.ru/crm/deal/details/510974/"target="_blank">Ссылка</a>
A75: 727 | B75: 46253 | C75: 524518 | D75: 108224 | E75: Закрыто и реализованно | F75: 502730 | G75: 5089965 | H75: Online ГК Диалог \ ООО "Управляющая компания Диалог" | I75: 1650207558 | J75: 63439.8 | K75: да | N75: 3171990 | O75: 63439.8 | P75: 26/08/19-01 | Q75: 46253 | R75: GEELY | S75: CITYRAY | T75: Новое | U75: LB3G43S99TX408062 | V75: 3171990 | W75: 63439.8 | X75: GEELY CITYRAY LB3G43S99TX408062 | Y75: Набережные Челны | Z75: 2026 | AA75: FALSE | AB75: <a href="https://sberauto.bitrix24.ru/crm/deal/details/524518/"target="_blank">Ссылка</a>
A76: 1209 | B76: 46242 | C76: 510934 | D76: 108224 | E76: Закрыто и реализованно | F76: 495196 | G76: 5023929 | H76: Online ГК Диалог \ ООО "Управляющая компания Диалог" | I76: 1650207558 | J76: 61000 | K76: да | N76: 3050000 | O76: 61000 | P76: ТТТ7103589125 | Q76: 46242 | R76: GEELY | S76: Cityray | T76: Новое | U76: LB3G43S93TX409353 | V76: 3050000 | W76: 61000 | X76: GEELY Cityray LB3G43S93TX409353 | Y76: Набережные Челны | Z76: 2026 | AA76: FALSE | AB76: <a href="https://sberauto.bitrix24.ru/crm/deal/details/510934/"target="_blank">Ссылка</a>
A77: 787 | B77: 46260 | C77: 523428 | D77: 108224 | E77: Закрыто и реализованно | F77: 501912 | G77: 5077493 | H77: Online ГК Диалог \ ООО "Управляющая компания Диалог" | I77: 1650207558 | J77: 58760 | K77: да | L77: кв изменено | N77: 2938000 | O77: 58760 | P77: 26/08/26-01 | Q77: 46260 | R77: JELAND | S77: J7 | T77: Новое | U77: EDXDD21B6TG020748 | V77: 2938000 | W77: 67000 | X77: JELAND J7 EDXDD21B6TG020748 | Y77: Казань | Z77: 2026 | AA77: FALSE | AB77: <a href="https://sberauto.bitrix24.ru/crm/deal/details/523428/"target="_blank">Ссылка</a>
A78: 223 | B78: 46264 | C78: 533146 | D78: 108224 | E78: Закрыто и реализованно | F78: 509614 | G78: 5150870 | H78: Online ГК Диалог \ ООО "Управляющая компания Диалог" | I78: 1650207558 | J78: 41600 | K78: да | N78: 2080000 | O78: 41600 | P78: 26/08/29-03 | Q78: 46263 | R78: JETOUR | S78: DASHING | T78: Новое | U78: EC3DCUFD1TC016301 | V78: 2080000 | W78: 41600 | X78: JETOUR DASHING EC3DCUFD1TC016301 | Y78: Казань | Z78: 2026 | AA78: FALSE | AB78: <a href="https://sberauto.bitrix24.ru/crm/deal/details/533146/"target="_blank">Ссылка</a>
A79: 418 | B79: 46259 | C79: 529412 | D79: 108224 | E79: Закрыто и реализованно | F79: 506662 | G79: 5124886 | H79: Online ГК Диалог \ ООО "Управляющая компания Диалог" | I79: 1650207558 | J79: 42300 | K79: да | N79: 2115000 | O79: 42300 | P79: 25/08/26-11 | Q79: 46259 | R79: JETOUR | S79: DASHING | T79: Новое | U79: EC3DCUFD6TC015676 | V79: 2115000 | W79: 42300 | X79: JETOUR DASHING EC3DCUFD6TC015676 | Y79: Набережные Челны | Z79: 2026 | AA79: FALSE | AB79: <a href="https://sberauto.bitrix24.ru/crm/deal/details/529412/"target="_blank">Ссылка</a>
A80: 721 | B80: 46254 | C80: 524586 | D80: 108224 | E80: Закрыто и реализованно | F80: 502788 | G80: 5090655 | H80: Online ГК Диалог \ ООО "Управляющая компания Диалог" | I80: 1650207558 | J80: 48000 | K80: да | N80: 2400000 | O80: 48000 | P80: 26/08/19-04 | Q80: 46253 | R80: JETOUR | S80: X70 PLUS | T80: Новое | U80: EC37CUSM8TC006027 | V80: 2400000 | W80: 48000 | X80: JETOUR X70PLUS EC37CUSM8TC006027 | Y80: Набережные Челны | Z80: 2026 | AA80: FALSE | AB80: <a href="https://sberauto.bitrix24.ru/crm/deal/details/524586/"target="_blank">Ссылка</a>
A81: 736 | B81: 46253 | C81: 524346 | D81: 108224 | E81: Закрыто и реализованно | F81: 502594 | G81: 5089402 | H81: Online ГК Диалог \ ООО "Управляющая компания Диалог" | I81: 1650207558 | J81: 42000 | K81: да | N81: 2100000 | O81: 42000 | P81: 26/08/19-03 | Q81: 46253 | R81: JETOUR | S81: DASHING | T81: Новое | U81: EC3DCUFD2TC015240 | V81: 2100000 | W81: 42000 | X81: JETOUR DASHING EC3DCUFD2TC015240 | Y81: Набережные Челны | Z81: 2026 | AA81: FALSE | AB81: <a href="https://sberauto.bitrix24.ru/crm/deal/details/524346/"target="_blank">Ссылка</a>
A82: 905 | B82: 46262 | C82: 517636 | D82: 108224 | E82: Закрыто и реализованно | F82: 500242 | G82: 5066937 | H82: Online ГК Диалог \ ООО "Управляющая компания Диалог" | I82: 1650207558 | J82: 42000 | K82: да | N82: 2100000 | O82: 42000 | P82: 26/08/15-01 | Q82: 46249 | R82: JETOUR | S82: DASHING | T82: Новое | U82: EC3DCUFD2TC015965 | V82: 2100000 | W82: 42000 | X82: Jetour Dashing EC3DCUFD2TC015965 | Y82: Набережные Челны | Z82: 2026 | AA82: FALSE | AB82: <a href="https://sberauto.bitrix24.ru/crm/deal/details/517636/"target="_blank">Ссылка</a>
A83: 934 | B83: 46249 | C83: 517230 | D83: 108224 | E83: Закрыто и реализованно | F83: 497784 | H83: Online ГК Диалог \ ООО "Управляющая компания Диалог" | I83: 1650207558 | J83: 45800 | K83: да | N83: 2290000 | O83: 45800 | P83: 26/08/14-02 | Q83: 46248 | R83: JETOUR | S83: X70 + | T83: Новое | U83: EC37CUSM3TC007084 | V83: 2290000 | W83: 45800 | X83: JETOUR X70PLUS EC37CUSM3TC007084 | Y83: Набережные Челны | Z83: 2026 | AA83: FALSE | AB83: <a href="https://sberauto.bitrix24.ru/crm/deal/details/517230/"target="_blank">Ссылка</a>
A84: 1363 | B84: 46239 | C84: 508300 | D84: 108224 | E84: Закрыто и реализованно | F84: 492396 | G84: 4974952 | H84: Online ГК Диалог \ ООО "Управляющая компания Диалог" | I84: 1650207558 | J84: 46200 | K84: да | N84: 2310000 | O84: 46200 | P84: 04/08/26-11 | Q84: 46238 | R84: JETOUR | S84: X70 PLUS | T84: Новое | U84: EC37CUSM5TC006180 | V84: 2310000 | W84: 46200 | X84: JETOUR X70PLUS EC37CUSM5TC006180 | Y84: Набережные Челны | Z84: 2026 | AA84: FALSE | AB84: <a href="https://sberauto.bitrix24.ru/crm/deal/details/508300/"target="_blank">Ссылка</a>
A85: 32 | B85: 46265 | C85: 535358 | D85: 108224 | E85: Закрыто и реализованно | F85: 511354 | G85: 5165720 | H85: Online ГК Диалог \ ООО "Управляющая компания Диалог" | I85: 1650207558 | J85: 36000 | K85: да | N85: 1800000 | O85: 36000 | P85: 26/08/31-13 | Q85: 46265 | R85: JETOUR | S85: DASHING | T85: Новое | U85: EC3DCUFD4TC015384 | V85: 1800000 | W85: 36000 | X85: JETOUR DASHING EC3DCUFD4TC015384 | Y85: Набережные Челны | Z85: 2026 | AA85: FALSE | AB85: <a href="https://sberauto.bitrix24.ru/crm/deal/details/535358/"target="_blank">Ссылка</a>
A86: 37 | B86: 46265 | C86: 535336 | D86: 108224 | E86: Закрыто и реализованно | F86: 511334 | G86: 3865746 | H86: Online ГК Диалог \ ООО "Управляющая компания Диалог" | I86: 1650207558 | J86: 36000 | K86: да | N86: 1800000 | O86: 36000 | P86: 26/08/31-14 | Q86: 46265 | R86: JETOUR | S86: DASHING | T86: Новое | U86: EC3DCUFD1TC015519 | V86: 1800000 | W86: 36000 | X86: JETOUR DASHING EC3DCUFD1TC015519 | Y86: Набережные Челны | Z86: 2026 | AA86: FALSE | AB86: <a href="https://sberauto.bitrix24.ru/crm/deal/details/535336/"target="_blank">Ссылка</a>
A87: 295 | B87: 46263 | C87: 531678 | D87: 108224 | E87: Закрыто и реализованно | F87: 508384 | G87: 5141985 | H87: Online ГК Диалог \ ООО "Управляющая компания Диалог" | I87: 1650207558 | J87: 42000 | K87: да | N87: 2100000 | O87: 42000 | P87: 26/08/28-01 | Q87: 46262 | R87: JETOUR | S87: DASHING | T87: Новое | U87: EC3DCUFD6TC014320 | V87: 2100000 | W87: 42000 | X87: JETOUR DASHING EC3DCUFD6TC014320 | Y87: Бугульма | Z87: 2026 | AA87: FALSE | AB87: <a href="https://sberauto.bitrix24.ru/crm/deal/details/531678/"target="_blank">Ссылка</a>
A88: 539 | B88: 46262 | C88: 527358 | D88: 108224 | E88: Закрыто и реализованно | F88: 505042 | G88: 5109856 | H88: Online ГК Диалог \ ООО "Управляющая компания Диалог" | I88: 1650207558 | J88: 49000 | K88: да | N88: 2450000 | O88: 49000 | P88: 26/08/23-02 | Q88: 46257 | R88: Jetour | S88: DASHING | T88: Новое | U88: EC3DLUFD2TC013052 | V88: 2450000 | W88: 49000 | X88: Jetour DASHING EC3DLUFD2TC013052 | Y88: НАБЕРЕЖНЫЕ ЧЕЛНЫ | Z88: 2026 | AA88: FALSE | AB88: <a href="https://sberauto.bitrix24.ru/crm/deal/details/527358/"target="_blank">Ссылка</a>
A89: 620 | B89: 46256 | C89: 526242 | D89: 108224 | E89: Закрыто и реализованно | F89: 504040 | G89: 5100851 | H89: Online ГК Диалог \ ООО "Управляющая компания Диалог" | I89: 1650207558 | J89: 45779.98 | K89: да | N89: 2288999 | O89: 45779.98 | P89: 26/08/21-01 | Q89: 46255 | R89: JETOUR | S89: X70PLUS | T89: Новое | U89: EC37CUSM5TC006762 | V89: 2288999 | W89: 45779.98 | X89: JETOUR X70PLUS EC37CUSM5TC006762 | Y89: НАБЕРЕЖНЫЕ ЧЕЛНЫ | Z89: 2026 | AA89: FALSE | AB89: <a href="https://sberauto.bitrix24.ru/crm/deal/details/526242/"target="_blank">Ссылка</a>
A90: 788 | B90: 46252 | C90: 523422 | D90: 108224 | E90: Закрыто и реализованно | F90: 501908 | G90: 5023749 | H90: Online ГК Диалог \ ООО "Управляющая компания Диалог" | I90: 1650207558 | J90: 50198 | K90: да | N90: 2509900 | O90: 50198 | P90: 26/08/13-01 | Q90: 46247 | R90: JETOUR | S90: DASHING | T90: Новое | U90: EC3DCUFD4TC016101 | V90: 2509900 | W90: 50198 | X90: JETOUR DASHING EC3DCUFD4TC016101 | Y90: Набережные Челны | Z90: 2026 | AA90: FALSE | AB90: <a href="https://sberauto.bitrix24.ru/crm/deal/details/523422/"target="_blank">Ссылка</a>
A91: 836 | B91: 46251 | C91: 518842 | D91: 108224 | E91: Закрыто и реализованно | F91: 501138 | G91: 5077483 | H91: Online ГК Диалог \ ООО "Управляющая компания Диалог" | I91: 1650207558 | J91: 47800 | K91: да | N91: 2390000 | O91: 47800 | P91: 17/08/26-11 | Q91: 46251 | R91: JETOUR | S91: X70PLUS | T91: Новое | U91: EC37CUSM8TC006187 | V91: 2390000 | W91: 47800 | X91: JETOUR X70PLUS EC37CUSM8TC006187 | Y91: НАБЕРЕЖНЫЕ ЧЕЛНЫ | Z91: 2026 | AA91: FALSE | AB91: <a href="https://sberauto.bitrix24.ru/crm/deal/details/518842/"target="_blank">Ссылка</a>
A92: 913 | B92: 46249 | C92: 517586 | D92: 108224 | E92: Закрыто и реализованно | F92: 500192 | G92: 5067993 | H92: Online ГК Диалог \ ООО "Управляющая компания Диалог" | I92: 1650207558 | J92: 45800 | K92: да | N92: 2290000 | O92: 45800 | P92: 15/08/26-44 | Q92: 46249 | R92: JETOUR | S92: X70PLUS | T92: Новое | U92: EC37CUSMXTC005994 | V92: 2290000 | W92: 45800 | X92: JETOUR X70PLUS EC37CUSMXTC005994 | Y92: Набережные Челны | Z92: 2026 | AA92: FALSE | AB92: <a href="https://sberauto.bitrix24.ru/crm/deal/details/517586/"target="_blank">Ссылка</a>
A93: 922 | B93: 46249 | C93: 517474 | D93: 108224 | E93: Закрыто и реализованно | F93: 500088 | G93: 5063159 | H93: Online ГК Диалог \ ООО "Управляющая компания Диалог" | I93: 1650207558 | J93: 43800 | K93: да | N93: 2190000 | O93: 43800 | P93: 26/08/14-07 | Q93: 46248 | R93: JETOUR | S93: X70 PLUS | T93: Новое | U93: EC37CUSM8TC006125 | V93: 2190000 | W93: 43800 | X93: JETOUR X70PLUS EC37CUSM8TC006125 | Y93: казань | Z93: 2026 | AA93: FALSE | AB93: <a href="https://sberauto.bitrix24.ru/crm/deal/details/517474/"target="_blank">Ссылка</a>
A94: 1026 | B94: 46246 | C94: 514902 | D94: 108224 | E94: Закрыто и реализованно | F94: 498024 | G94: 4760979 | H94: Online ГК Диалог \ ООО "Управляющая компания Диалог" | I94: 1650207558 | J94: 42000 | K94: да | N94: 2100000 | O94: 42000 | P94: 26/08/12-01 | Q94: 46246 | R94: JETOUR | S94: DASHING | T94: Новое | U94: EC3DCUFD3TC015876 | V94: 2100000 | W94: 42000 | X94: JETOUR DASHING EC3DCUFD3TC015876 | Y94: Казань | Z94: 2026 | AA94: FALSE | AB94: <a href="https://sberauto.bitrix24.ru/crm/deal/details/514902/"target="_blank">Ссылка</a>
A95: 1077 | B95: 46246 | C95: 513956 | D95: 108224 | E95: Закрыто и реализованно | F95: 497358 | G95: 4937412 | H95: Online ГК Диалог \ ООО "Управляющая компания Диалог" | I95: 1650207558 | J95: 42000 | K95: да | N95: 2100000 | O95: 42000 | P95: 26/08/11-01 | Q95: 46245 | R95: JETOUR | S95: DASHING | T95: Новое | U95: EC3DCUFD8TC015145 | V95: 2100000 | W95: 42000 | X95: JETOUR DASHING EC3DCUFD8TC015145 | Y95: Набережные Челны | Z95: 2026 | AA95: FALSE | AB95: <a href="https://sberauto.bitrix24.ru/crm/deal/details/513956/"target="_blank">Ссылка</a>
... A106: 1152 | B106: 46244 | C106: 512500 | D106: 84628 | E106: Закрыто и реализованно | F106: 496358 | G106: 5033090 | H106: ONLINE Апельсин (ООО "АПЕЛЬСИН-ЧЕЛНЫ") | I106: 1650392340 | J106: 48185 | K106: да | N106: 2409250 | O106: 48185 | P106: Ач00002573 | Q106: 46244 | R106: SOLARIS | S106: KRX | T106: Новое | U106: Z94C251BBSR200841 | V106: 2409250 | W106: 48185 | X106: Solaris KRX Z94C251BBSR200841 | Y106: Набережные Челны | Z106: 2026 | AA106: FALSE | AB106: <a href="https://sberauto.bitrix24.ru/crm/deal/details/512500/"target="_blank">Ссылка</a>
A107: 1480 | B107: 46241 | C107: 506512 | D107: 84628 | E107: Закрыто и реализованно | F107: 491684 | G107: 4670905 | H107: ONLINE Апельсин (ООО "АПЕЛЬСИН-ЧЕЛНЫ") | I107: 1650392340 | J107: 24060 | K107: да | L107: ИИ неверно посчитал | N107: 1203000 | O107: 18045 | P107: А400002515 | Q107: 46240 | R107: LADA | S107: GRANTA | T107: Новое | U107: XTA219140V0694638 | V107: 1203000 | W107: 18045 | X107: LADA GRANTA XTA219140V0694638 | Y107: Набережные Челны | Z107: 2026 | AA107: FALSE | AB107: <a href="https://sberauto.bitrix24.ru/crm/deal/details/506512/"target="_blank">Ссылка</a>
A108: 461 | B108: 46258 | C108: 528448 | D108: 95202 | E108: Закрыто и реализованно | F108: 77714 | G108: 5044204 | H108: ГК Апельсин \ Челны-Авто Чери | I108: 1650402781 | J108: 53700 | K108: да | L108: лид. ИИ неверно посчитал 1,5% | N108: 2685000 | O108: 40275 | P108: ЧА00001380 | Q108: 46256 | R108: Tenet | S108: t7 | T108: Новое | U108: EDEFB32BXTE098733 | V108: 2685000 | W108: 40275 | X108: Tenet t7 EDEFB32BXTE098733 | Y108: Набережные Челны | Z108: 2026 | AA108: FALSE | AB108: <a href="https://sberauto.bitrix24.ru/crm/deal/details/528448/"target="_blank">Ссылка</a>
A109: 670 | B109: 46254 | C109: 525446 | D109: 95202 | E109: Закрыто и реализованно | F109: 503446 | G109: 5095870 | H109: ГК Апельсин \ Челны-Авто Чери | I109: 1650402781 | J109: 45800 | K109: да | N109: 2290000 | O109: 45800 | P109: A00001365 | Q109: 46254 | R109: JETOUR | S109: X70 + | T109: Новое | U109: EC37CUSM1TC005768 | V109: 2290000 | W109: 45800 | X109: Jetour Х70+ EC37CUSM1TC005768 | Y109: Набережные Челны | Z109: 2026 | AA109: FALSE | AB109: <a href="https://sberauto.bitrix24.ru/crm/deal/details/525446/"target="_blank">Ссылка</a>
A110: 691 | B110: 46254 | C110: 525176 | D110: 95202 | E110: Закрыто и реализованно | F110: 503234 | G110: 5094242 | H110: ГК Апельсин \ Челны-Авто Чери | I110: 1650402781 | J110: 73400 | K110: да | L110: кв исправлено | N110: 3670000 | O110: 73400 | P110: ЧА00001363 | Q110: 46254 | R110: JETOUR | S110: Т1 | T110: Новое | U110: LVTDD24B4TDB72480 | V110: 3670000 | W110: 55050 | X110: Jetour T1 LVTDD24B4TDB72480 | Y110: Набережные Челны | Z110: 2026 | AA110: FALSE | AB110: <a href="https://sberauto.bitrix24.ru/crm/deal/details/525176/"target="_blank">Ссылка</a>
A111: 1229 | B111: 46242 | C111: 510754 | D111: 95202 | E111: Закрыто и реализованно | F111: 495034 | G111: 5023237 | H111: ГК Апельсин \ Челны-Авто Чери | I111: 1650402781 | J111: 49200 | K111: да | N111: 2460000 | O111: 49200 | P111: ЧА00001274 | Q111: 46242 | R111: Jetour | S111: Х70+ | T111: Новое | U111: EC37LUSM1TC005740 | V111: 2460000 | W111: 49200 | X111: Jetour Х70+ EC37LUSM1TC005740 | Y111: Набережные Челны | Z111: 2026 | AA111: FALSE | AB111: <a href="https://sberauto.bitrix24.ru/crm/deal/details/510754/"target="_blank">Ссылка</a>
A112: 1318 | B112: 46240 | C112: 509292 | D112: 95202 | E112: Закрыто и реализованно | F112: 493882 | G112: 4976185 | H112: ГК Апельсин \ Челны-Авто Чери | I112: 1650402781 | J112: 45866 | K112: да | N112: 2293300 | O112: 45866 | P112: ЧА00001264 | Q112: 46240 | R112: JETOUR | S112: X70 + | T112: Новое | U112: EC37CUSM9TC006O36 | V112: 2293300 | W112: 45866 | X112: JETOUR x70+ EC37CUSM9TC006O36 | Y112: Набережные Челны | Z112: 2026 | AA112: FALSE | AB112: <a href="https://sberauto.bitrix24.ru/crm/deal/details/509292/"target="_blank">Ссылка</a>
A113: 1399 | B113: 46238 | C113: 507386 | D113: 95202 | E113: Закрыто и реализованно | F113: 491996 | G113: 4874528 | H113: ГК Апельсин \ Челны-Авто Чери | I113: 1650402781 | J113: 42000 | K113: да | N113: 2100000 | O113: 42000 | P113: ЧА00001244 | Q113: 46238 | R113: Jetour | S113: Dashing | T113: Новое | U113: EC3DCUFD5TC015913 | V113: 2100000 | W113: 42000 | X113: Jetour Dashing EC3DCUFD5TC015913 | Y113: Набережные Челны | Z113: 2026 | AA113: FALSE | AB113: <a href="https://sberauto.bitrix24.ru/crm/deal/details/507386/"target="_blank">Ссылка</a>
A114: 1438 | B114: 46260 | C114: 506684 | D114: 95202 | E114: Закрыто и реализованно | F114: 491862 | G114: 4995654 | H114: ГК Апельсин \ Челны-Авто Чери | I114: 1650402781 | J114: 83400 | K114: да | N114: 4170000 | O114: 83400 | P114: ЧА00001247 | Q114: 46238 | R114: Jetour | S114: Т2 | T114: Новое | U114: EC3TDUMA3T0004282 | V114: 4170000 | W114: 83400 | X114: Jetour Т2 EC3TDUMA3T0004282 | Y114: Набережные Челны | Z114: 2026 | AA114: FALSE | AB114: <a href="https://sberauto.bitrix24.ru/crm/deal/details/506684/"target="_blank">Ссылка</a>
A115: 73 | B115: 46265 | C115: 534942 | D115: 112940 | E115: Закрыто и реализованно | F115: 511072 | G115: 196468 | H115: ООО "КАН АВТО-5" ONLINE | I115: 1657190695 | K115: да | N115: 2650000 | O115: 53000 | P115: ААК5-001373 | Q115: 46264 | R115: SOUEAST | S115: S06 | T115: Новое | U115: EC3DCUGA8TC000813 | V115: 2650000 | W115: 53000 | X115: SOUEAST S06 EC3DCUGA8TC000813 | Y115: Казань | Z115: 2026 | AA115: FALSE | AB115: <a href="https://sberauto.bitrix24.ru/crm/deal/details/534942/"target="_blank">Ссылка</a>
A116: 298 | B116: 46261 | C116: 531252 | D116: 112940 | E116: Закрыто и реализованно | F116: 508028 | G116: 5111361 | H116: ООО "КАН АВТО-5" ONLINE | I116: 1657190695 | K116: да | N116: 2350000 | O116: 47000 | P116: ААК5-001350 | Q116: 46261 | R116: JETOUR | S116: Х70+ | T116: Новое | U116: EC37LUSM3TC006257 | V116: 2350000 | W116: 47000 | X116: JETOUR Х70+ EC37LUSM3TC006257 | Y116: Казань | Z116: 2026 | AA116: FALSE | AB116: <a href="https://sberauto.bitrix24.ru/crm/deal/details/531252/"target="_blank">Ссылка</a>
A117: 390 | B117: 46260 | C117: 529708 | D117: 112940 | E117: Закрыто и реализованно | F117: 505846 | G117: 5116400 | H117: ООО "КАН АВТО-5" ONLINE | I117: 1657190695 | K117: да | N117: 2020000 | O117: 40400 | P117: ААК5-001331 | Q117: 46259 | R117: JETOUR | S117: DASHING | T117: Новое | U117: EC3DCUFD6TC011319 | V117: 2020000 | W117: 40400 | X117: JETOUR DASHING EC3DCUFD6TC011319 | Y117: Казань | Z117: 2026 | AA117: FALSE | AB117: <a href="https://sberauto.bitrix24.ru/crm/deal/details/529708/"target="_blank">Ссылка</a>
A118: 503 | B118: 46265 | C118: 527734 | D118: 112940 | E118: Закрыто и реализованно | F118: 505400 | G118: 5112372 | H118: ООО "КАН АВТО-5" ONLINE | I118: 1657190695 | K118: да | N118: 3549000 | O118: 70980 | P118: ААК5-001363 | Q118: 46263 | R118: JETOUR | S118: Т2 | T118: Новое | U118: EC3TEUMB3T0002733 | V118: 3549000 | W118: 70980 | X118: JETOUR Т2 EC3TEUMB3T0002733 | Y118: Казань | Z118: 2026 | AA118: FALSE | AB118: <a href="https://sberauto.bitrix24.ru/crm/deal/details/527734/"target="_blank">Ссылка</a>
A119: 581 | B119: 46257 | C119: 526756 | D119: 112940 | E119: Закрыто и реализованно | F119: 504494 | G119: 5105464 | H119: ООО "КАН АВТО-5" ONLINE | I119: 1657190695 | K119: да | N119: 2100000 | O119: 42000 | P119: ААК5-001311 | Q119: 46257 | R119: JETOUR | S119: DASHING | T119: Новое | U119: EC3DCUFD7TC011121 | V119: 2100000 | W119: 42000 | X119: JETOUR DASHING EC3DCUFD7TC011121 | Y119: Казань | Z119: 2026 | AA119: FALSE | AB119: <a href="https://sberauto.bitrix24.ru/crm/deal/details/526756/"target="_blank">Ссылка</a>
A120: 612 | B120: 46256 | C120: 526304 | D120: 112940 | E120: Закрыто и реализованно | F120: 504102 | G120: 5100899 | H120: ООО "КАН АВТО-5" ONLINE | I120: 1657190695 | K120: да | N120: 3740000 | O120: 74800 | P120: ААК5-001302 | Q120: 46256 | R120: JETOUR | S120: T2 | T120: Новое | U120: EC3TEUMB6T0003908 | V120: 3740000 | W120: 74800 | X120: JETOUR T2 EC3TEUMB6T0003908 | Y120: Казань | Z120: 2026 | AA120: FALSE | AB120: <a href="https://sberauto.bitrix24.ru/crm/deal/details/526304/"target="_blank">Ссылка</a>
A121: 1169 | B121: 46250 | C121: 511792 | D121: 113186 | E121: Закрыто и реализованно | F121: 495420 | G121: 5020529 | H121: ООО "СПЕКТР" ONLINE АВТОСЕТЬ РФ/Апельсин | I121: 1657225323 | J121: 49200 | K121: да | N121: 2460000 | O121: 49200 | P121: Сп00003336 | Q121: 46248 | R121: JETOUR | S121: X70 PLUS | T121: Новое | U121: EC37LUSMXTC006448 | V121: 2460000 | W121: 49200 | X121: JETOUR X70 PLUS EC37LUSMXTC006448 | Y121: Казань | Z121: 2026 | AA121: FALSE | AB121: <a href="https://sberauto.bitrix24.ru/crm/deal/details/511792/"target="_blank">Ссылка</a>
A122: 1327 | B122: 46240 | C122: 509058 | D122: 113186 | E122: Закрыто и реализованно | F122: 493366 | G122: 5012114 | H122: ООО "СПЕКТР" ONLINE АВТОСЕТЬ РФ/Апельсин | I122: 1657225323 | J122: 41000 | K122: да | N122: 2050000 | O122: 41000 | P122: СП00003186 | Q122: 46239 | R122: JETOUR | S122: DASHING | T122: Новое | U122: EC3DCUFD8TC010897 | V122: 2050000 | W122: 41000 | X122: JETOUR DASHING EC3DCUFD8TC010897 | Y122: Казань | Z122: 2026 | AA122: FALSE | AB122: <a href="https://sberauto.bitrix24.ru/crm/deal/details/509058/"target="_blank">Ссылка</a>
A123: 1500 | B123: 46238 | C123: 506376 | D123: 113186 | E123: Закрыто и реализованно | F123: 491590 | G123: 4993383 | H123: ООО "СПЕКТР" ONLINE АВТОСЕТЬ РФ/Апельсин | I123: 1657225323 | J123: 45800 | K123: да | N123: 2290000 | O123: 45800 | P123: СП00003153 | Q123: 46237 | R123: JETOUR | S123: X70 PLUS | T123: Новое | U123: EC37CUSM9SC003703 | V123: 2290000 | W123: 45800 | X123: JETOUR X70 PLUS EC37CUSM9SC003703 | Y123: КАЗАНЬ | Z123: 2026 | AA123: FALSE | AB123: <a href="https://sberauto.bitrix24.ru/crm/deal/details/506376/"target="_blank">Ссылка</a>
A124: 1507 | B124: 46238 | C124: 506328 | D124: 113186 | E124: Закрыто и реализованно | F124: 491554 | G124: 4227023 | H124: ООО "СПЕКТР" ONLINE АВТОСЕТЬ РФ/Апельсин | I124: 1657225323 | J124: 42000 | K124: да | N124: 2100000 | O124: 42000 | P124: СП00003155 | Q124: 46237 | R124: JETOUR | S124: DASHING | T124: Новое | U124: EC3DCUFD5TC016141 | V124: 2100000 | W124: 42000 | X124: JETOUR DASHING EC3DCUFD5TC016141 | Y124: КАЗАНЬ | Z124: 2026 | AA124: FALSE | AB124: <a href="https://sberauto.bitrix24.ru/crm/deal/details/506328/"target="_blank">Ссылка</a>
A125: 501 | B125: 46257 | C125: 527756 | D125: 112212 | E125: Закрыто и реализованно | F125: 505406 | G125: 5047737 | H125: ООО "ПАРУС" online | I125: 1659000597 | J125: 16995 | N125: 1133000 | O125: 16995 | P125: 865 | Q125: 46257 | R125: LADA | S125: GRANTA | T125: Новое | U125: XTA219040V1276564 | V125: 1133000 | W125: 16995 | X125: LADA GRANTA XTA219040V1276564 | Y125: Казань | Z125: 2026 | AA125: FALSE | AB125: <a href="https://sberauto.bitrix24.ru/crm/deal/details/527756/"target="_blank">Ссылка</a>
A126: 100 | B126: 46265 | C126: 534770 | D126: 112692 | E126: Закрыто и реализованно | F126: 510658 | G126: 5158839 | H126: ONLINE АО "БАРС АВТО" | I126: 1660075318 | J126: 54400 | N126: 2720000 | O126: 54400 | P126: 1164 | Q126: 46264 | R126: SOUEAST | S126: S06 | T126: Новое | U126: SQRF4J16CBPSK00231 | V126: 2720000 | W126: 54400 | X126: SOUEAST S06 SQRF4J16CBPSK00231 | Y126: Казань | Z126: 2026 | AA126: FALSE | AB126: <a href="https://sberauto.bitrix24.ru/crm/deal/details/534770/"target="_blank">Ссылка</a>
A127: 103 | B127: 46265 | C127: 534748 | D127: 112692 | E127: Закрыто и реализованно | F127: 510910 | G127: 5161832 | H127: ONLINE АО "БАРС АВТО" | I127: 1660075318 | J127: 75800 | N127: 3790000 | O127: 147420 | P127: 1152 | Q127: 46264 | R127: JETOUR | S127: T2 | T127: Новое | U127: EC3TEUMB1T0003900 | V127: 3790000 | W127: 147420 | X127: JETOUR T2 EC3TEUMB1T0003900 | Y127: Казань | Z127: 2026 | AA127: FALSE | AB127: <a href="https://sberauto.bitrix24.ru/crm/deal/details/534748/"target="_blank">Ссылка</a>
A128: 317 | B128: 46261 | C128: 531000 | D128: 112692 | E128: Закрыто и реализованно | F128: 507846 | G128: 5137540 | H128: ONLINE АО "БАРС АВТО" | I128: 1660075318 | J128: 75000 | N128: 3750000 | O128: 75000 | P128: 1149 | Q128: 46261 | R128: JETOUR | S128: X90PLUS | T128: Новое | U128: EC3SLU2A7T0000480 | V128: 3750000 | W128: 75000 | X128: JETOUR X90PLUS EC3SLU2A7T0000480 | Y128: Казань | Z128: 2026 | AA128: FALSE | AB128: <a href="https://sberauto.bitrix24.ru/crm/deal/details/531000/"target="_blank">Ссылка</a>
A129: 453 | B129: 46258 | C129: 528536 | D129: 112692 | E129: Закрыто и реализованно | F129: 505978 | G129: 5117864 | H129: ONLINE АО "БАРС АВТО" | I129: 1660075318 | J129: 74400 | N129: 3720000 | O129: 74400 | P129: 1138 | Q129: 46258 | R129: JETOUR | S129: Т2 | T129: Новое | U129: EC3TEUMB7T0002671 | V129: 3720000 | W129: 74400 | X129: Jetour Т2 EC3TEUMB7T0002671 | Y129: Казань | Z129: 2026 | AA129: FALSE | AB129: <a href="https://sberauto.bitrix24.ru/crm/deal/details/528536/"target="_blank">Ссылка</a>
A130: 469 | B130: 46258 | C130: 528326 | D130: 112692 | E130: Закрыто и реализованно | F130: 505818 | G130: 5116775 | H130: ONLINE АО "БАРС АВТО" | I130: 1660075318 | J130: 42000 | N130: 2100000 | O130: 42000 | P130: 1137 | Q130: 46258 | R130: JETOUR | S130: DASHING | T130: Новое | U130: EC3DCUFD9TC010360 | V130: 2100000 | W130: 42000 | X130: Jetour Dashing EC3DCUFD9TC010360 | Y130: Казань | Z130: 2026 | AA130: FALSE | AB130: <a href="https://sberauto.bitrix24.ru/crm/deal/details/528326/"target="_blank">Ссылка</a>
A131: 553 | B131: 46256 | C131: 527040 | D131: 112692 | E131: Закрыто и реализованно | F131: 504776 | G131: 5106926 | H131: ONLINE АО "БАРС АВТО" | I131: 1660075318 | J131: 73400 | N131: 3670000 | O131: 73400 | P131: 1097 | Q131: 46256 | R131: Jetour | S131: Т1 | T131: Новое | U131: LVTDD24BXTDB86755 | V131: 3670000 | W131: 73400 | X131: Jetour Т1 LVTDD24BXTDB86755 | Y131: Казань | Z131: 2026 | AA131: FALSE | AB131: <a href="https://sberauto.bitrix24.ru/crm/deal/details/527040/"target="_blank">Ссылка</a>
A132: 748 | B132: 46260 | C132: 524164 | D132: 112692 | E132: Закрыто и реализованно | F132: 502462 | G132: 5088451 | H132: ONLINE АО "БАРС АВТО" | I132: 1660075318 | J132: 73140 | N132: 3657000 | O132: 73140 | P132: 1108 | Q132: 46253 | R132: JETOUR | S132: Т1 | T132: Новое | U132: LVTDD24B9TDB99593 | V132: 3657000 | W132: 73140 | X132: Jetour T1 LVTDD24B9TDB99593 | Y132: Казань | Z132: 2026 | AA132: FALSE | AB132: <a href="https://sberauto.bitrix24.ru/crm/deal/details/524164/"target="_blank">Ссылка</a>
A133: 965 | B133: 46248 | C133: 516764 | D133: 112692 | E133: Закрыто и реализованно | F133: 499542 | G133: 5060717 | H133: ONLINE АО "БАРС АВТО" | I133: 1660075318 | J133: 42000 | N133: 2100000 | O133: 42000 | P133: 1077 | Q133: 46248 | R133: JETOUR | S133: DASHING | T133: Новое | U133: EC3DCUFD6TC016004 | V133: 2100000 | W133: 42000 | X133: JETOUR DASHING EC3DCUFD6TC016004 | Y133: Казань | Z133: 2026 | AA133: FALSE | AB133: <a href="https://sberauto.bitrix24.ru/crm/deal/details/516764/"target="_blank">Ссылка</a>
A134: 1241 | B134: 46241 | C134: 510336 | D134: 112692 | E134: Закрыто и реализованно | F134: 493754 | G134: 5011027 | H134: ONLINE АО "БАРС АВТО" | I134: 1660075318 | J134: 42000 | N134: 2100000 | O134: 42000 | P134: 1040 | Q134: 46240 | R134: JETOUR | S134: DASHING | T134: Новое | U134: EC3DCUFDXTC016037 | V134: 2100000 | W134: 42000 | X134: JETOUR DASHING EC3DCUFDXTC016037 | Y134: Казань | Z134: 2026 | AA134: FALSE | AB134: <a href="https://sberauto.bitrix24.ru/crm/deal/details/510336/"target="_blank">Ссылка</a>
A135: 1429 | B135: 46237 | C135: 506762 | D135: 112692 | E135: Закрыто и реализованно | F135: 491924 | G135: 4971125 | H135: ONLINE АО "БАРС АВТО" | I135: 1660075318 | J135: 39400 | N135: 1970000 | O135: 39400 | P135: 1009 | Q135: 46234 | R135: JETOUR | S135: DASHING | T135: Новое | U135: EC3DCUFD7TC014729 | V135: 1970000 | W135: 39400 | X135: JETOUR DASHING EC3DCUFD7TC014729 | Y135: КАЗАНЬ | Z135: 2026 | AA135: FALSE | AB135: <a href="https://sberauto.bitrix24.ru/crm/deal/details/506762/"target="_blank">Ссылка</a>
A136: 1430 | B136: 46237 | C136: 506752 | D136: 112692 | E136: Закрыто и реализованно | F136: 126132 | G136: 4971093 | H136: ONLINE АО "БАРС АВТО" | I136: 1660075318 | J136: 39400 | N136: 1970000 | O136: 39400 | P136: 1010 | Q136: 46234 | R136: JETOUR | S136: DASHING | T136: Новое | U136: EC3DCUFD7TC014732 | V136: 1970000 | W136: 39400 | X136: JETOUR DASHING EC3DCUFD7TC014732 | Y136: Казань | Z136: 2026 | AA136: FALSE | AB136: <a href="https://sberauto.bitrix24.ru/crm/deal/details/506752/"target="_blank">Ссылка</a>
... A150: 1671 | B150: 46251 | C150: 484582 | D150: 112770 | E150: Закрыто и реализованно | F150: 475652 | G150: 4837183 | H150: ООО "ДАТ Р" online | I150: 1660106816 | J150: 44000 | N150: 2200000 | O150: 44000 | P150: 1120 | Q150: 46213 | R150: Soueast | S150: S06 | T150: Новое | U150: EC3DCUFD4TC000433 | V150: 2200000 | W150: 44000 | X150: Soueast S06 EC3DCUFD4TC000433 | Y150: Ростов-на-Дону | Z150: 2026 | AA150: FALSE | AB150: <a href="https://sberauto.bitrix24.ru/crm/deal/details/484582/"target="_blank">Ссылка</a>
A151: 164 | B151: 46264 | C151: 534212 | D151: 112828 | E151: Закрыто и реализованно | F151: 499862 | G151: 4040470 | H151: ООО "КАН АВТО-21" ONLINE | I151: 1685007616 | J151: 31425 | N151: 2095000 | O151: 31425 | P151: АА1К-001170 | Q151: 46262 | R151: LADA | S151: VESTA | T151: Новое | U151: XTAGFK110V1061538 | V151: 2095000 | W151: 31425 | X151: LADA VESTA XTAGFK110V1061538 | Y151: Казань | Z151: 2026 | AA151: FALSE | AB151: <a href="https://sberauto.bitrix24.ru/crm/deal/details/534212/"target="_blank">Ссылка</a>
A152: 172 | B152: 46264 | C152: 534138 | D152: 101950 | E152: Закрыто и реализованно | F152: 504146 | G152: 3431950 | H152: ONLINE LADA Русская Ладья (ООО "РУССКАЯ ЛАДЬЯ") | I152: 1831158253 | J152: 29550 | N152: 1970000 | O152: 29550 | P152: 31-11136837 | Q152: 46260 | R152: LADA | S152: VESTA | T152: Новое | U152: XTAGFL360V1063223 | V152: 1970000 | W152: 29550 | X152: Lada Vesta XTAGFL360V1063223 | Y152: Ижевск | Z152: 2026 | AA152: FALSE | AB152: <a href="https://sberauto.bitrix24.ru/crm/deal/details/534138/"target="_blank">Ссылка</a>
A153: 1090 | B153: 46245 | C153: 513722 | D153: 102442 | E153: Закрыто и реализованно | F153: 497166 | G153: 4569844 | H153: ONLINE ИНТЕРПАРТНЕР (ООО ФИРМА "ИНТЕРПАРТНЕР") | I153: 1835035118 | N153: 2990000 | O153: 44850 | P153: ЦБ161734/ЧОН | Q153: 46233 | R153: TENET | S153: T7 | T153: Новое | U153: EDXFD32B5TE092453 | V153: 2990000 | W153: 44850 | X153: TENET T7 EDXFD32B5TE092453 | Y153: Ижевск | Z153: 2026 | AA153: FALSE | AB153: <a href="https://sberauto.bitrix24.ru/crm/deal/details/513722/"target="_blank">Ссылка</a>
A154: 72 | B154: 46265 | C154: 534956 | D154: 109428 | E154: Закрыто и реализованно | F154: 511082 | G154: 4356560 | H154: ONLINE ООО "АВТОМАРКЕТ" | I154: 1841096486 | J154: 75400 | N154: 3770000 | O154: 30000 | P154: ЦБ096145 | Q154: 46265 | R154: JETOUR | S154: T1 | T154: Новое | U154: LVTDD24B6TDB98899 | V154: 3770000 | W154: 30000 | X154: JETOUR Х70+ LVTDD24B6TDB98899 | Y154: Ижевск | Z154: 2026 | AA154: FALSE | AB154: <a href="https://sberauto.bitrix24.ru/crm/deal/details/534956/"target="_blank">Ссылка</a>
A155: 82 | B155: 46265 | C155: 534870 | D155: 109428 | E155: Закрыто и реализованно | F155: 511018 | G155: 5162528 | H155: ONLINE ООО "АВТОМАРКЕТ" | I155: 1841096486 | J155: 42000 | N155: 2100000 | O155: 30000 | P155: ЦБ095431 | Q155: 46265 | R155: JETOUR | S155: DASHING | T155: Новое | U155: EC3DCUFD2TC015769 | V155: 2100000 | W155: 30000 | X155: JETOUR DASHING EC3DCUFD2TC015769 | Y155: Ижевск | Z155: 2026 | AA155: FALSE | AB155: <a href="https://sberauto.bitrix24.ru/crm/deal/details/534870/"target="_blank">Ссылка</a>
A156: 115 | B156: 46265 | C156: 534658 | D156: 109428 | E156: Закрыто и реализованно | F156: 510838 | G156: 5161406 | H156: ONLINE ООО "АВТОМАРКЕТ" | I156: 1841096486 | J156: 45800 | N156: 2290000 | O156: 30000 | P156: ЦБ096129 | Q156: 46265 | R156: JETOUR | S156: X70PLUS | T156: Новое | U156: EC37CUSM8TC007145 | V156: 2290000 | W156: 30000 | X156: JETOUR X70PLUS EC37CUSM8TC007145 | Y156: Ижевск | Z156: 2026 | AA156: FALSE | AB156: <a href="https://sberauto.bitrix24.ru/crm/deal/details/534658/"target="_blank">Ссылка</a>
A157: 253 | B157: 46263 | C157: 532556 | D157: 109428 | E157: Закрыто и реализованно | F157: 509100 | G157: 5148690 | H157: ONLINE ООО "АВТОМАРКЕТ" | I157: 1841096486 | J157: 49200 | N157: 2460000 | O157: 30000 | P157: ЦБ095302 | Q157: 46263 | R157: JETOUR | S157: X70 + | T157: Новое | U157: EC37LUSM5TC006678 | V157: 2460000 | W157: 30000 | X157: Jetour X70+ EC37LUSM5TC006678 | Y157: Ижевск | Z157: 2026 | AA157: FALSE | AB157: <a href="https://sberauto.bitrix24.ru/crm/deal/details/532556/"target="_blank">Ссылка</a>
A158: 387 | B158: 46260 | C158: 529728 | D158: 109428 | E158: Закрыто и реализованно | F158: 506870 | G158: 1847040 | H158: ONLINE ООО "АВТОМАРКЕТ" | I158: 1841096486 | J158: 51000 | N158: 2550000 | O158: 51000 | P158: ЦБ095874 | Q158: 46260 | R158: SOUEAST | S158: S06 | T158: Новое | U158: EC3DCUGA1TC000801 | V158: 2550000 | W158: 51000 | X158: SOUEAST S06 EC3DCUGA1TC000801 | Y158: Ижевск | Z158: 2026 | AA158: FALSE | AB158: <a href="https://sberauto.bitrix24.ru/crm/deal/details/529728/"target="_blank">Ссылка</a>
A159: 491 | B159: 46265 | C159: 528082 | D159: 109428 | E159: Закрыто и реализованно | F159: 505646 | G159: 5115445 | H159: ONLINE ООО "АВТОМАРКЕТ" | I159: 1841096486 | J159: 45800 | N159: 2290000 | O159: 30000 | P159: ЦБ095404 | Q159: 46258 | R159: Jetour | S159: X70 + | T159: Новое | U159: EC37CUSM9TC006778 | V159: 2290000 | W159: 30000 | X159: Jetour X70 + EC37CUSM9TC006778 | Y159: ИЖЕВСК | Z159: 2026 | AA159: FALSE | AB159: <a href="https://sberauto.bitrix24.ru/crm/deal/details/528082/"target="_blank">Ссылка</a>
...

Sheet Дилеры_ИЮЛЬ
B1: client_id | C1: Название компании | D1: ИНН | E1: Цена | F1: КВ. Авто | G1: кв по реестру | H1: Комментарий | I1: Номер ДКП | J1: Дата ДКП | K1: brand | L1: model | M1: TYPE | N1: VIN | O1: Цена | P1: КВ. Авто | Q1: Время закрытия | R1: Deal_ID | S1: Contact_ID | T1: Название стадии | U1: Идентификатор компании | V1: Название товара | W1: CITY | X1: YEAR | Y1: Error | Z1: Ссылка на сделку
A2: 1308 | B2: 4321933 | C2: ONLINE CHERY Автолюкс (ООО "АВТОЛЮКС") | D2: =VLOOKUP(U2,Лист1!A:B,2,0) -> 2630048453 | E2: 3478000 | F2: 117475 | G2: =E2-F2 -> 3360525 | H2: формула | I2: ПЛ000000162 | J2: 46218 | K2: TENET | L2: T8 | M2: Новое | N2: EDEGD34B0SE049468 | O2: 3478000 | P2: 117475 | Q2: 46218 | R2: 481122 | S2: 473272 | T2: Закрыто и реализованно | U2: 82506 | V2: TENET T8 EDEGD34B0SE049468 | W2: Пятигорск | X2: 2026 | Y2: FALSE | Z2: <a href="https://sberauto.bitrix24.ru/crm/deal/details/481122/"target="_blank">Ссылка</a>
A3: 907 | B3: 4858987 | C3: ООО "ДЕБРЯНСК АВТО" ONLINE | D3: =VLOOKUP(U3,Лист1!A:B,2,0) -> 3250521481 | E3: 2214000 | F3: 67950 | G3: =E3-F3 -> 2146050 | H3: формула | I3: 178426 | J3: 46223 | K3: TENET | L3: T4L | M3: Новое | N3: EDELB31BXTE062593 | O3: 2214000 | P3: 67950 | Q3: 46223 | R3: 491010 | S3: 480036 | T3: Закрыто и реализованно | U3: 112892 | V3: Tenet T4L EDELB31BXTE062593 | W3: Брянск | X3: 2026 | Y3: FALSE | Z3: <a href="https://sberauto.bitrix24.ru/crm/deal/details/491010/"target="_blank">Ссылка</a>
A4: 1307 | B4: 4807154 | C4: ONLINE АГАТ CHERY/O&J (ООО "АВТО-КОНТИНЕНТ") | D4: =VLOOKUP(U4,Лист1!A:B,2,0) -> 3804048079 | E4: 3478000 | F4: 117475 | G4: =E4-F4 -> 3360525 | H4: формула | I4: АНТ002788 | J4: 46210 | K4: TENET | L4: T8 | M4: Новое | N4: EDXGD34B2TE888059 | O4: 3478000 | P4: 117475 | Q4: 46227 | R4: 481158 | S4: 471972 | T4: Закрыто и реализованно | U4: 101276 | V4: TENET T8 EDXGD34B2TE888059 | W4: Иркутск | X4: 2026 | Y4: FALSE | Z4: <a href="https://sberauto.bitrix24.ru/crm/deal/details/481158/"target="_blank">Ссылка</a>
A5: 218 | B5: 2252719 | C5: ООО "Кунцево Авто Трейдинг" (ООО "КУНЦЕВО АТ") Online | D5: =VLOOKUP(U5,Лист1!A:B,2,0) -> 5032271860 | E5: 2613000 | F5: 88900 | G5: =E5-F5 -> 2524100 | H5: формула | I5: CHR0000879 | J5: 46231 | K5: TENET | L5: T7 | M5: Новое | N5: EDXFB32B1TE087241 | O5: 2613000 | P5: 88900 | Q5: 46232 | R5: 501646 | S5: 485214 | T5: Закрыто и реализованно | U5: 107748 | V5: TENET T7 EDXFB32B1TE087241 | W5: Москва | X5: 2026 | Y5: FALSE | Z5: <a href="https://sberauto.bitrix24.ru/crm/deal/details/501646/"target="_blank">Ссылка</a>
A6: 1277 | B6: 4794021 | C6: ООО КУНЦЕВО АТ | D6: 5032271860 | E6: 2214000 | F6: 67950 | G6: =E6-F6 -> 2146050 | H6: формула | I6: CHR0000801 | J6: 46211 | K6: Tenet | L6: T4L | M6: Новое | N6: EDELB31B3TE071037 | O6: 2214000 | P6: 67950 | Q6: 46224 | R6: 481484 | S6: 473544 | T6: Закрыто и реализованно | U6: 112222 | V6: Tenet T4L EDELB31B3TE071037 | W6: Москва | X6: 2026 | Y6: FALSE | Z6: <a href="https://sberauto.bitrix24.ru/crm/deal/details/481484/"target="_blank">Ссылка</a>
A7: 435 | B7: 4342624 | C7: АО "РОЛЬФ" ONLINE | D7: =VLOOKUP(U7,Лист1!A:B,2,0) -> 5047254063 | E7: 2494000 | F7: 54000 | G7: =E7-F7 -> 2440000 | H7: формула | I7: ОМ028013 | J7: 46229 | K7: Jaecoo | L7: J6 | M7: Новое | N7: EDXDB21B6TG025275 | O7: 2494000 | P7: 54000 | Q7: 46231 | R7: 498382 | S7: 485510 | T7: Закрыто и реализованно | U7: 111670 | V7: Jaecoo J6 EDXDB21B6TG025275 | W7: Москва | X7: 2026 | Y7: FALSE | Z7: <a href="https://sberauto.bitrix24.ru/crm/deal/details/498382/"target="_blank">Ссылка</a>
A8: 364 | B8: 1246289 | C8: ONLINE CHERY/TENET Нижегородец (ООО "НИЖЕГОРОДЕЦ ВОСТОК") | D8: =VLOOKUP(U8,Лист1!A:B,2,0) -> 5257164835 | E8: 2613000 | F8: 88900 | G8: =E8-F8 -> 2524100 | H8: формула | I8: 0203306/02-H | J8: 46229 | K8: TENET | L8: Т7 | M8: Новое | N8: EDXFB32B1TE084310 | O8: 2613000 | P8: 88900 | Q8: 46230 | R8: 499656 | S8: 481266 | T8: Закрыто и реализованно | U8: 89154 | V8: Tenet T7 EDXFB32B1TE084310 | W8: Нижний Новгород | X8: 2026 | Y8: FALSE | Z8: <a href="https://sberauto.bitrix24.ru/crm/deal/details/499656/"target="_blank">Ссылка</a>
A9: 1377 | B9: 4803511 | C9: ONLINE CHERY/TENET Нижегородец (ООО "НИЖЕГОРОДЕЦ ВОСТОК") | D9: =VLOOKUP(U9,Лист1!A:B,2,0) -> 5257164835 | E9: 2529000 | F9: 88800 | G9: =E9-F9 -> 2440200 | H9: формула | I9: 0199321/02-H | J9: 46207 | K9: TENET | L9: T7 | M9: Новое | N9: EDXFD32B2TE039726 | O9: 2529000 | P9: 88800 | Q9: 46208 | R9: 478854 | S9: 471466 | T9: Закрыто и реализованно | U9: 89154 | V9: TENET T7 EDXFD32B2TE039726 | W9: Нижний Новгород | X9: 2026 | Y9: FALSE | Z9: <a href="https://sberauto.bitrix24.ru/crm/deal/details/478854/"target="_blank">Ссылка</a>
A10: 1009 | B10: 4615723 | C10: ONLINE ЛунаАвто (ООО "ЛУНААВТО") | D10: =VLOOKUP(U10,Лист1!A:B,2,0) -> 5410065297 | E10: 2906000 | F10: 94200 | G10: =E10-F10 -> 2811800 | H10: формула | I10: 00000000926 | J10: 46221 | K10: Tenet | L10: T7 | M10: Новое | N10: EDXFD32B5TE080142 | O10: 2906000 | P10: 94200 | Q10: 46223 | R10: 488416 | S10: 478080 | T10: Закрыто и реализованно | U10: 75574 | V10: Tenet T7 EDXFD32B5TE080142 | W10: Новосибирск | X10: 2026 | Y10: FALSE | Z10: <a href="https://sberauto.bitrix24.ru/crm/deal/details/488416/"target="_blank">Ссылка</a>
A11: 1246 | B11: 4823955 | C11: ONLINE ЧЕРИ ЦЕНТР ТЕМП АВТО ДОН (ООО "ТЕМП АВТО ДОН") | D11: =VLOOKUP(U11,Лист1!A:B,2,0) -> 6155046305 | E11: 2549010 | F11: 88800 | G11: =E11-F11 -> 2460210 | H11: формула | I11: 11181 | J11: 46215 | K11: Tenet | L11: T7 | M11: Новое | N11: EDXFD32B7TE046803 | O11: 2549010 | P11: 88800 | Q11: 46217 | R11: 482572 | S11: 474326 | T11: Закрыто и реализованно | U11: 75462 | V11: Tenet T7 EDXFD32B7TE046803 | W11: Ростов-На-Дону | X11: 2026 | Y11: FALSE | Z11: <a href="https://sberauto.bitrix24.ru/crm/deal/details/482572/"target="_blank">Ссылка</a>
A12: 1258 | B12: 4565354 | C12: ONLINE CHERY Автофорум (ООО "АВТОФОРУМ ЦЕНТР") | D12: =VLOOKUP(U12,Лист1!A:B,2,0) -> 6452947574 | E12: 2529000 | F12: 88800 | G12: =E12-F12 -> 2440200 | H12: формула | I12: 000001026 | J12: 46212 | K12: TENET | L12: T7 | M12: Новое | N12: EDXFD32B0TE043306 | O12: 2529000 | P12: 88800 | Q12: 46213 | R12: 482312 | S12: 474156 | T12: Закрыто и реализованно | U12: 93280 | V12: TENET T7 EDXFD32B0TE043306 | W12: Саратов | X12: 2026 | Y12: FALSE | Z12: <a href="https://sberauto.bitrix24.ru/crm/deal/details/482312/"target="_blank">Ссылка</a>
A13: 813 | B13: 4836243 | C13: ONLINE ЧЕРИ ЦЕНТР ПЛАНЕТА АВТО ВОСТОК (ООО "АВТОГАРАНТИЯ") | D13: =VLOOKUP(U13,Лист1!A:B,2,0) -> 7447124619 | E13: 2529000 | F13: 88800 | G13: =E13-F13 -> 2440200 | H13: формула | I13: 1523 F/T | J13: 46197 | K13: Tenet | L13: T7 | M13: Новое | N13: EDXFD32B9TE047211 | O13: 2529000 | P13: 88800 | Q13: 46234 | R13: 494018 | S13: 476864 | T13: Закрыто и реализованно | U13: 101774 | V13: Tenet T7 EDXFD32B9TE047211 | W13: Челябинск | X13: 2026 | Y13: FALSE | Z13: <a href="https://sberauto.bitrix24.ru/crm/deal/details/494018/"target="_blank">Ссылка</a>
A14: 1352 | B14: 4477163 | C14: ONLINE ЧЕРИ ЦЕНТР ПЛАНЕТА АВТО ВОСТОК (ООО "АВТОГАРАНТИЯ") | D14: =VLOOKUP(U14,Лист1!A:B,2,0) -> 7447124619 | E14: 2855600 | F14: 94200 | G14: =E14-F14 -> 2761400 | H14: формула | I14: 1647 F/T | J14: 46212 | K14: Tenet | L14: T7 | M14: Новое | N14: EDXFD32BXTE079357 | O14: 2855600 | P14: 94200 | Q14: 46217 | R14: 479664 | S14: 472268 | T14: Закрыто и реализованно | U14: 101774 | V14: Tenet T7 EDXFD32BXTE079357 | W14: Челябинск | X14: 2026 | Y14: FALSE | Z14: <a href="https://sberauto.bitrix24.ru/crm/deal/details/479664/"target="_blank">Ссылка</a>
A15: 1263 | B15: 4815867 | C15: ООО "СИГМА АВТО" | D15: =VLOOKUP(U15,Лист1!A:B,2,0) -> 7813649997 | E15: 3078000 | F15: 105000 | G15: =E15-F15 -> 2973000 | H15: формула | I15: САЗА-015082 | J15: 46212 | K15: OMODA | L15: C7 | M15: Новое | N15: EDEKD32B6TE055676 | O15: 3078000 | P15: 105000 | Q15: 46223 | R15: 482022 | S15: 481592 | T15: Закрыто и реализованно | U15: 80978 | V15: OMODA C7 EDEKD32B6TE055676 | W15: Санкт-Петербург | X15: 2026 | Y15: FALSE | Z15: <a href="https://sberauto.bitrix24.ru/crm/deal/details/482022/"target="_blank">Ссылка</a>
A16: 208 | B16: 4917519 | C16: ООО "МС МОТОРС ЗУБОВО" ONLINE | D16: =VLOOKUP(U16,Лист1!A:B,2,0) -> 245961925 | E16: 2270000 | F16: 45400 | I16: 26/07-34/ам | J16: 46228 | K16: Jetour | L16: X70+ | M16: Новое | N16: EC37LUSM8TC005444 | O16: 2270000 | P16: 45400 | Q16: 46233 | R16: 502032 | S16: 488282 | T16: Закрыто и реализованно | U16: 113078 | V16: Jetour X70+ EC37LUSM8TC005444 | W16: РЕСПУБЛИКА БАШКОРТОСТАН УФИМСКИЙ С. ЗУБОВО | X16: 2026 | Y16: FALSE | Z16: <a href="https://sberauto.bitrix24.ru/crm/deal/details/502032/"target="_blank">Ссылка</a>
A17: 216 | B17: 4894679 | C17: ООО "МС МОТОРС ЗУБОВО" ONLINE | D17: =VLOOKUP(U17,Лист1!A:B,2,0) -> 245961925 | E17: 3708900 | F17: 74178 | I17: 26/07-30/АМ | J17: 46226 | K17: Jetour | L17: Т2 | M17: Новое | N17: EC3TEUMB0T0003922 | O17: 3708900 | P17: 74178 | Q17: 46232 | R17: 501674 | S17: 487974 | T17: Закрыто и реализованно | U17: 113078 | V17: Jetour Т2 EC3TEUMB0T0003922 | W17: Уфа | X17: 2026 | Y17: FALSE | Z17: <a href="https://sberauto.bitrix24.ru/crm/deal/details/501674/"target="_blank">Ссылка</a>
A18: 1006 | B18: 4856024 | C18: ООО "МС МОТОРС ЗУБОВО" ONLINE | D18: =VLOOKUP(U18,Лист1!A:B,2,0) -> 245961925 | E18: 3660000 | F18: 73200 | I18: 26/07-33/АМ | J18: 46227 | K18: JETOUR | L18: T2 | M18: Новое | N18: EC3TEUMB0T0002818 | O18: 3660000 | P18: 73200 | Q18: 46233 | R18: 488530 | S18: 478436 | T18: Закрыто и реализованно | U18: 113078 | V18: JETOUR T2 EC3TEUMB0T0002818 | W18: Зубово | X18: 2026 | Y18: FALSE | Z18: <a href="https://sberauto.bitrix24.ru/crm/deal/details/488530/"target="_blank">Ссылка</a>
A19: 1079 | B19: 3395055 | C19: Online ООО Автосеть Уфа | D19: =VLOOKUP(U19,Лист1!A:B,2,0) -> 276945049 | E19: 2733000 | F19: 40995 | H19: стандарт отчет | I19: УФ000001709 | J19: 46224 | K19: TENET | L19: Т7 | M19: Новое | N19: EDXFB32B8TE087186 | O19: 2733000 | P19: 40995 | Q19: 46227 | R19: 487416 | S19: 477370 | T19: Закрыто и реализованно | U19: 86024 | V19: Tenet T7 EDXFB32B8TE087186 | W19: Уфа | X19: 2026 | Y19: FALSE | Z19: <a href="https://sberauto.bitrix24.ru/crm/deal/details/487416/"target="_blank">Ссылка</a>
A20: 19 | B20: 2744728 | C20: Прагматика (ПЕТРОЗАВОДСК-ЛАДА) | D20: =VLOOKUP(U20,Лист1!A:B,2,0) -> 1001340114 | E20: 1930000 | F20: 19300 | I20: 31-11024446-КП | J20: 46234 | K20: LADA | L20: Niva | M20: Новое | N20: XTA212310T1000785 | O20: 1930000 | P20: 19300 | Q20: 46234 | R20: 505410 | S20: 448486 | T20: Закрыто и реализованно | U20: 95208 | V20: LADA Niva XTA212310T1000785 | W20: Москва | X20: 2026 | Y20: FALSE | Z20: <a href="https://sberauto.bitrix24.ru/crm/deal/details/505410/"target="_blank">Ссылка</a>
A21: 25 | B21: 4851281 | C21: Online ООО "ЛЕОН" | D21: =VLOOKUP(U21,Лист1!A:B,2,0) -> 1207901941 | E21: 3974000 | F21: 79480 | I21: ДТ-43 | J21: 46233 | K21: JETOUR | L21: Т1 | M21: Новое | N21: LVTDD24B7TDC00840 | O21: 3974000 | P21: 79480 | Q21: 46234 | R21: 505338 | S21: 485970 | T21: Закрыто и реализованно | U21: 112880 | V21: JETOUR Т1 LVTDD24B7TDC00840 | W21: Медведево | X21: 2026 | Y21: FALSE | Z21: <a href="https://sberauto.bitrix24.ru/crm/deal/details/505338/"target="_blank">Ссылка</a>
A22: 961 | B22: 4861970 | C22: Online ООО "ЛЕОН" | D22: =VLOOKUP(U22,Лист1!A:B,2,0) -> 1207901941 | E22: 2270000 | F22: 45400 | H22: не наш клиент отмена кв | I22: ДТ-38 | J22: 46219 | K22: Jetour | L22: X70+ | M22: Новое | N22: EC37LUSM5TC004994 | O22: 2270000 | P22: 45400 | Q22: 46219 | R22: 489484 | S22: 479090 | T22: Закрыто и реализованно | U22: 112880 | V22: Jetour X70+ EC37LUSM5TC004994 | W22: Йошкар-Ола | X22: 2026 | Y22: FALSE | Z22: <a href="https://sberauto.bitrix24.ru/crm/deal/details/489484/"target="_blank">Ссылка</a>
A23: 1322 | B23: 4814824 | C23: ООО "КОНДОР-ПЛЮС" ONLINE | D23: =VLOOKUP(U23,Лист1!A:B,2,0) -> 1215185868 | E23: 2244000 | F23: 44880 | I23: 21-26-О | J23: 46210 | K23: Jetour | L23: X70+ | M23: Новое | N23: EC37LUSM7SC003439 | O23: 2244000 | P23: 44880 | Q23: 46210 | R23: 480494 | S23: 472842 | T23: Закрыто и реализованно | U23: 112548 | V23: Jetour X70+ EC37LUSM7SC003439 | W23: Йошкар - Ола | X23: 2025 | Y23: FALSE | Z23: <a href="https://sberauto.bitrix24.ru/crm/deal/details/480494/"target="_blank">Ссылка</a>
A24: 607 | B24: 4911640 | C24: ООО "КМ-АВТО САРАНСК-2" ONLINE | D24: =VLOOKUP(U24,Лист1!A:B,2,0) -> 1300005883 | E24: 2900000 | F24: 58000 | I24: М000000066 | J24: 46227 | K24: SOLARIS | L24: HC | M24: Новое | N24: Z94PF814BSR072863 | O24: 2900000 | P24: 58000 | Q24: 46234 | R24: 496762 | S24: 484190 | T24: Закрыто и реализованно | U24: 111882 | V24: SOLARIS HC Z94PF814BSR072863 | X24: 2025 | Y24: TRUE | Z24: <a href="https://sberauto.bitrix24.ru/crm/deal/details/496762/"target="_blank">Ссылка</a>
A25: 769 | B25: 4631928 | C25: ООО "КМ-АВТО САРАНСК-2" ONLINE | D25: =VLOOKUP(U25,Лист1!A:B,2,0) -> 1300005883 | E25: 3303000 | F25: 66060 | I25: М000000065 | J25: 46218 | K25: SOLARIS | L25: HC | M25: Новое | N25: Z94PC815DSR069291 | O25: 3303000 | P25: 66060 | Q25: 46234 | R25: 494746 | S25: 482770 | T25: Закрыто и реализованно | U25: 111882 | V25: SOLARIS HC Z94PC815DSR069291 | W25: Саранск | X25: 2025 | Y25: FALSE | Z25: <a href="https://sberauto.bitrix24.ru/crm/deal/details/494746/"target="_blank">Ссылка</a>
A26: 929 | B26: 4874758 | C26: ООО "КМ-АВТО САРАНСК-2" ONLINE | D26: =VLOOKUP(U26,Лист1!A:B,2,0) -> 1300005883 | E26: 2772000 | F26: 55440 | I26: М000000064 | J26: 46221 | K26: Solaris | L26: HC | M26: Новое | N26: Z94PB814BSR071971 | O26: 2772000 | P26: 55440 | Q26: 46223 | R26: 490046 | S26: 479520 | T26: Закрыто и реализованно | U26: 111882 | V26: Solaris HC Z94PB814BSR071971 | W26: Саранск | X26: 2025 | Y26: FALSE | Z26: <a href="https://sberauto.bitrix24.ru/crm/deal/details/490046/"target="_blank">Ссылка</a>
A27: 994 | B27: 4866202 | C27: ООО "КМ-АВТО САРАНСК-2" ONLINE | D27: =VLOOKUP(U27,Лист1!A:B,2,0) -> 1300005883 | E27: 2350000 | F27: 47000 | I27: М0000000б3 | J27: 46218 | K27: SOLARIS | L27: KRS | M27: Новое | N27: Z94C241BBSR272703 | O27: 2350000 | P27: 47000 | Q27: 46218 | R27: 488710 | S27: 478606 | T27: Закрыто и реализованно | U27: 111882 | V27: SOLARIS KRS Z94C241BBSR272703 | W27: Саранск | X27: 2025 | Y27: FALSE | Z27: <a href="https://sberauto.bitrix24.ru/crm/deal/details/488710/"target="_blank">Ссылка</a>
A28: 1362 | B28: 4808170 | C28: ООО "КМ-АВТО САРАНСК-2" ONLINE | D28: =VLOOKUP(U28,Лист1!A:B,2,0) -> 1300005883 | E28: 3235000 | F28: 64700 | I28: М000000060 | J28: 46206 | K28: SOLARIS | L28: HC | M28: Новое | N28: Z94PC815BSR071911 | O28: 3235000 | P28: 64700 | Q28: 46234 | R28: 478996 | S28: 471766 | T28: Закрыто и реализованно | U28: 111882 | V28: SOLARIS HC Z94PC815BSR071911 | W28: Саранск | X28: 2025 | Y28: FALSE | Z28: <a href="https://sberauto.bitrix24.ru/crm/deal/details/478996/"target="_blank">Ссылка</a>
A29: 1404 | B29: 4804089 | C29: ООО "КМ-АВТО САРАНСК-2" ONLINE | D29: =VLOOKUP(U29,Лист1!A:B,2,0) -> 1300005883 | E29: 3235000 | F29: 64700 | H29: дубль сделки (закрыта дважды на мужа и жену) | I29: М000000060 | J29: 46206 | K29: SOLARIS | L29: HC | M29: Новое | N29: Z94PC815BSR071911 | O29: 3235000 | P29: 64700 | Q29: 46212 | R29: 478190 | S29: 471102 | T29: Закрыто и реализованно | U29: 111882 | V29: SOLARIS HC Z94PC815BSR071911 | W29: Саранск | X29: 2025 | Y29: FALSE | Z29: <a href="https://sberauto.bitrix24.ru/crm/deal/details/478190/"target="_blank">Ссылка</a>
A30: 842 | B30: 4889422 | C30: ООО "АРМАДА-АВТО" online | D30: =VLOOKUP(U30,Лист1!A:B,2,0) -> 1615009225 | E30: 3253750 | F30: 65075 | I30: АА00000810 | J30: 46232 | K30: Solaris | L30: HC | M30: Новое | N30: Z94PC815DSR072244 | O30: 3253750 | P30: 65075 | Q30: 46232 | R30: 493752 | S30: 482058 | T30: Закрыто и реализованно | U30: 112710 | V30: Solaris HC Z94PC815DSR072244 | W30: Нижнекамск | X30: 2025 | Y30: FALSE | Z30: <a href="https://sberauto.bitrix24.ru/crm/deal/details/493752/"target="_blank">Ссылка</a>
A31: 939 | B31: 4865992 | C31: ООО "АРМАДА-АВТО" online | D31: =VLOOKUP(U31,Лист1!A:B,2,0) -> 1615009225 | E31: 2290000 | F31: 45800 | I31: 685/2026 | J31: 46229 | K31: Jetour | L31: X70+ | M31: Новое | N31: EC37LUSM6TC006253 | O31: 2290000 | P31: 45800 | Q31: 46230 | R31: 489806 | S31: 479352 | T31: Закрыто и реализованно | U31: 112710 | V31: Jetour X70+ EC37LUSM6TC006253 | W31: Екатеринбург | X31: 2026 | Y31: FALSE | Z31: <a href="https://sberauto.bitrix24.ru/crm/deal/details/489806/"target="_blank">Ссылка</a>
A32: 940 | B32: 485637 | C32: ООО "АРМАДА-АВТО" online | D32: =VLOOKUP(U32,Лист1!A:B,2,0) -> 1615009225 | E32: 2290000 | F32: 45800 | I32: 663/2026 | J32: 46224 | K32: Jetour | L32: Х70+ | M32: Новое | N32: EC37LUSM4TC005344 | O32: 2290000 | P32: 45800 | Q32: 46227 | R32: 489800 | S32: 479338 | T32: Закрыто и реализованно | U32: 112710 | V32: Jetour Х70+ EC37LUSM4TC005344 | W32: Екатеренбург | X32: 2026 | Y32: FALSE | Z32: <a href="https://sberauto.bitrix24.ru/crm/deal/details/489800/"target="_blank">Ссылка</a>
A33: 1366 | B33: 4761427 | C33: ООО "АРМАДА-АВТО" online | D33: =VLOOKUP(U33,Лист1!A:B,2,0) -> 1615009225 | E33: 2270000 | F33: 45400 | I33: АА00000735 | J33: 46212 | K33: JETOUR | L33: X70+ | M33: Новое | N33: EC37LUSMXSC003595 | O33: 2270000 | P33: 45400 | Q33: 46233 | R33: 478958 | S33: 471736 | T33: Закрыто и реализованно | U33: 112710 | V33: Jetour X70+ EC37LUSMXSC003595 | W33: Нижнекамск | X33: 2026 | Y33: FALSE | Z33: <a href="https://sberauto.bitrix24.ru/crm/deal/details/478958/"target="_blank">Ссылка</a>
A34: 197 | B34: 4951688 | C34: ONLINE ООО "ДИАЛОГ АВТО" | D34: =VLOOKUP(U34,Лист1!A:B,2,0) -> 1644062657 | E34: 2300000 | F34: 46000 | I34: 29/07/26-11 | J34: 46232 | K34: JETOUR | L34: X70+ | M34: Новое | N34: EC37LUSM4TC006557 | O34: 2300000 | P34: 46000 | Q34: 46233 | R34: 502136 | S34: 488358 | T34: Закрыто и реализованно | U34: 107326 | V34: JETOUR X70PLUS EC37LUSM4TC006557 | X34: 2026 | Y34: TRUE | Z34: <a href="https://sberauto.bitrix24.ru/crm/deal/details/502136/"target="_blank">Ссылка</a>
A35: 382 | B35: 4935425 | C35: ONLINE ООО "ДИАЛОГ АВТО" | D35: =VLOOKUP(U35,Лист1!A:B,2,0) -> 1644062657 | E35: 2230000 | F35: 44600 | I35: 26/07/27-01 | J35: 46230 | K35: JETOUR | L35: X70+ | M35: Новое | N35: EC37CUSMXTC005963 | O35: 2230000 | P35: 44600 | Q35: 46231 | R35: 499414 | S35: 486346 | T35: Закрыто и реализованно | U35: 107326 | V35: JETOUR X70+ EC37CUSMXTC005963 | X35: 2026 | Y35: TRUE | Z35: <a href="https://sberauto.bitrix24.ru/crm/deal/details/499414/"target="_blank">Ссылка</a>
A36: 426 | B36: 4929653 | C36: ONLINE ООО "ДИАЛОГ АВТО" | D36: =VLOOKUP(U36,Лист1!A:B,2,0) -> 1644062657 | E36: 3385000 | F36: 67700 | I36: 26/07/26-01 | J36: 46229 | K36: SOLARIS | L36: HC | M36: Новое | N36: Z94PC815DSR052827 | O36: 3385000 | P36: 67700 | Q36: 46230 | R36: 498478 | S36: 485592 | T36: Закрыто и реализованно | U36: 107326 | V36: SOLARIS HC Z94PC815DSR052827 | W36: Казань | X36: 2025 | Y36: FALSE | Z36: <a href="https://sberauto.bitrix24.ru/crm/deal/details/498478/"target="_blank">Ссылка</a>
A37: 533 | B37: 4923711 | C37: ONLINE ООО "ДИАЛОГ АВТО" | D37: =VLOOKUP(U37,Лист1!A:B,2,0) -> 1644062657 | E37: 2040000 | F37: 40800 | I37: TTT7091172177 | J37: 46228 | K37: JETOUR | L37: DASHING | M37: Новое | N37: EC3DCUFD7TC010521 | O37: 2040000 | P37: 40800 | Q37: 46233 | R37: 497420 | S37: 484704 | T37: Закрыто и реализованно | U37: 107326 | V37: JETOUR DASHING EC3DCUFD7TC010521 | W37: Казань | X37: 2026 | Y37: FALSE | Z37: <a href="https://sberauto.bitrix24.ru/crm/deal/details/497420/"target="_blank">Ссылка</a>
A38: 557 | B38: 4920996 | C38: ONLINE ООО "ДИАЛОГ АВТО" | D38: =VLOOKUP(U38,Лист1!A:B,2,0) -> 1644062657 | E38: 2040000 | F38: 40800 | I38: 26/07/24-01 | J38: 46227 | K38: JETOUR | L38: DASHING | M38: Новое | N38: EC3DCUFD7TC011037 | O38: 2040000 | P38: 40800 | Q38: 46231 | R38: 497034 | S38: 484412 | T38: Закрыто и реализованно | U38: 107326 | V38: JETOUR DASHING EC3DCUFD7TC011037 | W38: Казань | X38: 2026 | Y38: FALSE | Z38: <a href="https://sberauto.bitrix24.ru/crm/deal/details/497034/"target="_blank">Ссылка</a>
A39: 559 | B39: 4920882 | C39: ONLINE ООО "ДИАЛОГ АВТО" | D39: =VLOOKUP(U39,Лист1!A:B,2,0) -> 1644062657 | E39: 2070000 | F39: 41400 | I39: 26/07/24-11 | J39: 46227 | K39: JETOUR | L39: DASHING | M39: Новое | N39: EC3DCUFD6TC010784 | O39: 2070000 | P39: 41400 | Q39: 46231 | R39: 497014 | S39: 484396 | T39: Закрыто и реализованно | U39: 107326 | V39: JETOUR DASHING EC3DCUFD6TC010784 | W39: Казань | X39: 2026 | Y39: FALSE | Z39: <a href="https://sberauto.bitrix24.ru/crm/deal/details/497014/"target="_blank">Ссылка</a>
A40: 771 | B40: 452010 | C40: ONLINE ГК Диалог \ ООО Диалог Авто | D40: =VLOOKUP(U40,Лист1!A:B,2,0) -> 1644062657 | E40: 1970000 | F40: 39400 | I40: 26/07/21-01 | J40: 46224 | K40: Jetour | L40: Dashing | M40: Новое | N40: EC3DCUFD6TC010557 | O40: 1970000 | P40: 39400 | Q40: 46226 | R40: 494736 | S40: 482758 | T40: Закрыто и реализованно | U40: 108228 | V40: Jetour Dashing EC3DCUFD6TC010557 | W40: Набережные челны | X40: 2026 | Y40: FALSE | Z40: <a href="https://sberauto.bitrix24.ru/crm/deal/details/494736/"target="_blank">Ссылка</a>
A41: 836 | B41: 4895509 | C41: ONLINE ГК Диалог \ ООО Диалог Авто | D41: =VLOOKUP(U41,Лист1!A:B,2,0) -> 1644062657 | E41: 1970000 | F41: 39400 | I41: 26/07/20-03 | J41: 46223 | K41: JETOUR | L41: DASHING | M41: Новое | N41: EC3DCUFD4TC010377 | O41: 1970000 | P41: 39400 | Q41: 46225 | R41: 493800 | S41: 482096 | T41: Закрыто и реализованно | U41: 108228 | V41: JETOUR DASHING EC3DCUFD4TC010377 | W41: Казань | X41: 2026 | Y41: FALSE | Z41: <a href="https://sberauto.bitrix24.ru/crm/deal/details/493800/"target="_blank">Ссылка</a>
A42: 843 | B42: 4884137 | C42: ONLINE ГК Диалог \ ООО Диалог Авто | D42: =VLOOKUP(U42,Лист1!A:B,2,0) -> 1644062657 | E42: 6254100 | F42: 125082 | I42: 26/07/18-01 | J42: 46221 | K42: GAC | L42: S9 | M42: Новое | N42: LMGJF3S83T1000395 | O42: 6254100 | P42: 125082 | Q42: 46224 | R42: 493730 | S42: 482048 | T42: Закрыто и реализованно | U42: 108228 | V42: GAC S9 LMGJF3S83T1000395 | W42: Казань | X42: 2026 | Y42: FALSE | Z42: <a href="https://sberauto.bitrix24.ru/crm/deal/details/493730/"target="_blank">Ссылка</a>
A43: 874 | B43: 4880363 | C43: ONLINE ГК Диалог \ ООО Диалог Авто | D43: =VLOOKUP(U43,Лист1!A:B,2,0) -> 1644062657 | E43: 5600000 | F43: 112000 | I43: 26/07/17-03 | J43: 46220 | K43: GAC | L43: S7 | M43: Новое | N43: LMGNC3S81T1001622 | O43: 5600000 | P43: 112000 | Q43: 46224 | R43: 492878 | S43: 481566 | T43: Закрыто и реализованно | U43: 108228 | V43: Gac S7 LMGNC3S81T1001622 | W43: Казань | X43: 2026 | Y43: FALSE | Z43: <a href="https://sberauto.bitrix24.ru/crm/deal/details/492878/"target="_blank">Ссылка</a>
A44: 1045 | B44: 4857511 | C44: ONLINE ООО "ДИАЛОГ АВТО" | D44: =VLOOKUP(U44,Лист1!A:B,2,0) -> 1644062657 | E44: 2700000 | F44: 54000 | I44: 26/07/14-02 | J44: 46217 | K44: SOLARIS | L44: НС | M44: Новое | N44: Z94PB814BSR070331 | O44: 2700000 | P44: 54000 | Q44: 46218 | R44: 487774 | S44: 477888 | T44: Закрыто и реализованно | U44: 107326 | V44: SOLARIS НС Z94PB814BSR070331 | W44: Казань | X44: 2025 | Y44: FALSE | Z44: <a href="https://sberauto.bitrix24.ru/crm/deal/details/487774/"target="_blank">Ссылка</a>
A45: 1100 | B45: 4845390 | C45: ONLINE ГК Диалог \ ООО Диалог Авто | D45: =VLOOKUP(U45,Лист1!A:B,2,0) -> 1644062657 | E45: 2880000 | F45: 57600 | I45: 26/07/12-01 | J45: 46215 | K45: Solaris | L45: HC | M45: Новое | N45: Z94PB814CSR073240 | O45: 2880000 | P45: 57600 | Q45: 46218 | R45: 485960 | S45: 476610 | T45: Закрыто и реализованно | U45: 108228 | V45: Solaris HC Z94PB814CSR073240 | W45: Казань | X45: 2025 | Y45: FALSE | Z45: <a href="https://sberauto.bitrix24.ru/crm/deal/details/485960/"target="_blank">Ссылка</a>
A46: 1133 | B46: 3451753 | C46: ONLINE ГК Диалог \ ООО Диалог Авто | D46: =VLOOKUP(U46,Лист1!A:B,2,0) -> 1644062657 | E46: 2578000 | F46: 51560 | I46: 26/07/11-11 | J46: 46214 | K46: SOLARIS | L46: НС | M46: Новое | N46: Z94PB814ASR073129 | O46: 2578000 | P46: 51560 | Q46: 46218 | R46: 485224 | S46: 476074 | T46: Закрыто и реализованно | U46: 108228 | V46: SOLARIS НС Z94PB814ASR073129 | W46: Альметьевск | X46: 2025 | Y46: FALSE | Z46: <a href="https://sberauto.bitrix24.ru/crm/deal/details/485224/"target="_blank">Ссылка</a>
A47: 1250 | B47: 4822562 | C47: ONLINE ООО "ДИАЛОГ АВТО" | D47: =VLOOKUP(U47,Лист1!A:B,2,0) -> 1644062657 | E47: 2637000 | F47: 52740 | I47: 26/07/08-01 | J47: 46211 | K47: Solaris | L47: HC | M47: Новое | N47: Z94PB814ASR073357 | O47: 2637000 | P47: 52740 | Q47: 46218 | R47: 482530 | S47: 474298 | T47: Закрыто и реализованно | U47: 107326 | V47: Solaris HC Z94PB814ASR073357 | W47: Альметьевск | X47: 2025 | Y47: FALSE | Z47: <a href="https://sberauto.bitrix24.ru/crm/deal/details/482530/"target="_blank">Ссылка</a>
... A51: 161 | B51: 4958024 | C51: ONLINE ДИАЛОГ А | D51: =VLOOKUP(U51,Лист1!A:B,2,0) -> 1649021206 | E51: 2070000 | F51: 41400 | I51: 26/07/30-01 | J51: 46233 | K51: JETOUR | L51: DASHING | M51: Новое | N51: EC3DCUFD9TC010326 | O51: 2070000 | P51: 41400 | Q51: 46233 | R51: 502350 | S51: 488516 | T51: Закрыто и реализованно | U51: 102862 | V51: JETOUR DASHING EC3DCUFD9TC010326 | W51: Казань | X51: 2026 | Y51: FALSE | Z51: <a href="https://sberauto.bitrix24.ru/crm/deal/details/502350/"target="_blank">Ссылка</a>
A52: 191 | B52: 4952284 | C52: ONLINE ДИАЛОГ А | D52: =VLOOKUP(U52,Лист1!A:B,2,0) -> 1649021206 | E52: 1970000 | F52: 39400 | I52: 26/07/29-02 | J52: 46232 | K52: JETOUR | L52: DASHING | M52: Новое | N52: EC3DCUFD4TC010511 | O52: 1970000 | P52: 39400 | Q52: 46233 | R52: 502180 | S52: 488390 | T52: Закрыто и реализованно | U52: 102862 | V52: JETOUR DASHING EC3DCUFD4TC010511 | X52: 2026 | Y52: TRUE | Z52: <a href="https://sberauto.bitrix24.ru/crm/deal/details/502180/"target="_blank">Ссылка</a>
A53: 207 | B53: 4951008 | C53: ONLINE ДИАЛОГ А | D53: =VLOOKUP(U53,Лист1!A:B,2,0) -> 1649021206 | E53: 2100000 | F53: 42000 | I53: 26/07/29-02 | J53: 46232 | K53: JETOUR | L53: X70+ | M53: Новое | N53: EC37CUSM8TC006741 | O53: 2100000 | P53: 42000 | Q53: 46233 | R53: 502040 | S53: 488294 | T53: Закрыто и реализованно | U53: 102862 | V53: JETOUR X70PLUS EC37CUSM8TC006741 | W53: Казань | X53: 2026 | Y53: FALSE | Z53: <a href="https://sberauto.bitrix24.ru/crm/deal/details/502040/"target="_blank">Ссылка</a>
A54: 294 | B54: 3441267 | C54: ONLINE ДИАЛОГ А | D54: =VLOOKUP(U54,Лист1!A:B,2,0) -> 1649021206 | E54: 5309100 | F54: 106182 | I54: 26/07/11-01 | J54: 46214 | K54: GAC | L54: S7 | M54: Новое | N54: LMGNC3S51T1001397 | O54: 5309100 | P54: 106182 | Q54: 46232 | R54: 500920 | S54: 16254 | T54: Закрыто и реализованно | U54: 102862 | V54: GAC S7 LMGNC3S51T1001397 | W54: КАЗАНЬ | X54: 2026 | Y54: FALSE | Z54: <a href="https://sberauto.bitrix24.ru/crm/deal/details/500920/"target="_blank">Ссылка</a>
A55: 306 | B55: 4941781 | C55: ONLINE ДИАЛОГ А | D55: =VLOOKUP(U55,Лист1!A:B,2,0) -> 1649021206 | E55: 6000000 | F55: 120000 | I55: 26/07/28-01 | J55: 46231 | K55: GAC | L55: S7 | M55: Новое | N55: LMGNC3S88T1001634 | O55: 6000000 | P55: 120000 | Q55: 46232 | R55: 500850 | S55: 487384 | T55: Закрыто и реализованно | U55: 102862 | V55: GAC S7 LMGNC3S88T1001634 | X55: 2026 | Y55: TRUE | Z55: <a href="https://sberauto.bitrix24.ru/crm/deal/details/500850/"target="_blank">Ссылка</a>
A56: 412 | B56: 4283385 | C56: ONLINE ДИАЛОГ А | D56: =VLOOKUP(U56,Лист1!A:B,2,0) -> 1649021206 | E56: 2300000 | F56: 46000 | I56: 26/07/26-01 | J56: 46229 | K56: JETOUR | L56: X70PLUS | M56: Новое | N56: EC37CUSMXTC005896 | O56: 2300000 | P56: 46000 | Q56: 46231 | R56: 498630 | S56: 485700 | T56: Закрыто и реализованно | U56: 102862 | V56: JETOUR X70PLUS EC37CUSMXTC005896 | W56: Казань | X56: 2026 | Y56: FALSE | Z56: <a href="https://sberauto.bitrix24.ru/crm/deal/details/498630/"target="_blank">Ссылка</a>
A57: 437 | B57: 4929086 | C57: ONLINE ДИАЛОГ А | D57: =VLOOKUP(U57,Лист1!A:B,2,0) -> 1649021206 | E57: 2047800 | F57: 40956 | I57: 26/07/26-01 | J57: 46229 | K57: JETOUR | L57: DASHING | M57: Новое | N57: EC3DCUFD7SC008198 | O57: 2047800 | P57: 40956 | Q57: 46230 | R57: 498352 | S57: 485486 | T57: Закрыто и реализованно | U57: 102862 | V57: JETOUR DASHING EC3DCUFD7SC008198 | W57: Казань | X57: 2026 | Y57: FALSE | Z57: <a href="https://sberauto.bitrix24.ru/crm/deal/details/498352/"target="_blank">Ссылка</a>
A58: 482 | B58: 4925345 | C58: ONLINE ДИАЛОГ А | D58: =VLOOKUP(U58,Лист1!A:B,2,0) -> 1649021206 | E58: 2270000 | F58: 45400 | I58: 25/07/26-22 | J58: 46228 | K58: Jetour | L58: X70+ | M58: Новое | N58: EC37LUSM7TC0064103 | O58: 2270000 | P58: 45400 | Q58: 46228 | R58: 497776 | S58: 484990 | T58: Закрыто и реализованно | U58: 102862 | V58: Jetour X70+ EC37LUSM7TC0064103 | W58: Набережные Челны | X58: 2026 | Y58: FALSE | Z58: <a href="https://sberauto.bitrix24.ru/crm/deal/details/497776/"target="_blank">Ссылка</a>
A59: 501 | B59: 4924737 | C59: ONLINE ДИАЛОГ А | D59: =VLOOKUP(U59,Лист1!A:B,2,0) -> 1649021206 | E59: 2270000 | F59: 45400 | I59: 26/07/25-02 | J59: 46228 | K59: Jetour | L59: X70+ | M59: Новое | N59: EC37LUSM6TC006463 | O59: 2270000 | P59: 45400 | Q59: 46228 | R59: 497646 | S59: 484880 | T59: Закрыто и реализованно | U59: 102862 | V59: Jetour X70+ EC37LUSM6TC006463 | W59: Казань | X59: 2026 | Y59: FALSE | Z59: <a href="https://sberauto.bitrix24.ru/crm/deal/details/497646/"target="_blank">Ссылка</a>
A60: 520 | B60: 4924145 | C60: ONLINE ДИАЛОГ А | D60: =VLOOKUP(U60,Лист1!A:B,2,0) -> 1649021206 | E60: 3350000 | F60: 67000 | I60: 26/07/25-01 | J60: 46228 | K60: Gac | L60: GS4 | M60: Новое | N60: LMGAE3G52T1004536 | O60: 3350000 | P60: 67000 | Q60: 46228 | R60: 497506 | S60: 484774 | T60: Закрыто и реализованно | U60: 102862 | V60: Gac GS4 LMGAE3G52T1004536 | W60: Казань | X60: 2026 | Y60: FALSE | Z60: <a href="https://sberauto.bitrix24.ru/crm/deal/details/497506/"target="_blank">Ссылка</a>
A61: 612 | B61: 4908798 | C61: ONLINE ДИАЛОГ А | D61: =VLOOKUP(U61,Лист1!A:B,2,0) -> 1649021206 | E61: 1970000 | F61: 39400 | I61: 26/07/22-05 | J61: 46225 | K61: JETOUR | L61: DASHING | M61: Новое | N61: EC3DCUFD8TC010799 | O61: 1970000 | P61: 39400 | Q61: 46227 | R61: 496716 | S61: 483930 | T61: Закрыто и реализованно | U61: 102862 | V61: JETOUR DASHING EC3DCUFD8TC010799 | W61: Казань | X61: 2026 | Y61: FALSE | Z61: <a href="https://sberauto.bitrix24.ru/crm/deal/details/496716/"target="_blank">Ссылка</a>
A62: 614 | B62: 4919345 | C62: ONLINE ДИАЛОГ А | D62: =VLOOKUP(U62,Лист1!A:B,2,0) -> 1649021206 | E62: 5800000 | F62: 116000 | I62: 26/07/24-01 | J62: 46227 | K62: Gac | L62: S7 | M62: Новое | N62: LMGNC3S8XT1002039 | O62: 5800000 | P62: 116000 | Q62: 46228 | R62: 496704 | S62: 484160 | T62: Закрыто и реализованно | U62: 102862 | V62: Gac S7 LMGNC3S8XT1002039 | W62: Казань | X62: 2026 | Y62: FALSE | Z62: <a href="https://sberauto.bitrix24.ru/crm/deal/details/496704/"target="_blank">Ссылка</a>
A63: 615 | B63: 4830961 | C63: ONLINE ДИАЛОГ А | D63: =VLOOKUP(U63,Лист1!A:B,2,0) -> 1649021206 | E63: 5650000 | F63: 113000 | I63: 26/07/24-03 | J63: 46227 | K63: Gac | L63: S7 | M63: Новое | N63: LMGNC3S88T1001696 | O63: 5650000 | P63: 113000 | Q63: 46228 | R63: 496698 | S63: 475066 | T63: Закрыто и реализованно | U63: 102862 | V63: Gac S7 LMGNC3S88T1001696 | W63: Казань | X63: 2026 | Y63: FALSE | Z63: <a href="https://sberauto.bitrix24.ru/crm/deal/details/496698/"target="_blank">Ссылка</a>
A64: 700 | B64: 4907850 | C64: ONLINE ДИАЛОГ А | D64: =VLOOKUP(U64,Лист1!A:B,2,0) -> 1649021206 | E64: 4255000 | F64: 42550 | I64: 26/07/22-02 | J64: 46225 | K64: GAC | L64: GS 8 | M64: Новое | N64: LMGJU3G85T1063660 | O64: 4255000 | P64: 42550 | Q64: 46228 | R64: 496188 | S64: 483796 | T64: Закрыто и реализованно | U64: 102862 | V64: GAC GS 8 LMGJU3G85T1063660 | W64: Казань | X64: 2026 | Y64: FALSE | Z64: <a href="https://sberauto.bitrix24.ru/crm/deal/details/496188/"target="_blank">Ссылка</a>
A65: 701 | B65: 4907863 | C65: ONLINE ДИАЛОГ А | D65: =VLOOKUP(U65,Лист1!A:B,2,0) -> 1649021206 | E65: 5800000 | F65: 116000 | I65: 26/07/22-03 | J65: 46225 | K65: GAC | L65: S7 | M65: Новое | N65: LMGNC3S82T1001936 | O65: 5800000 | P65: 116000 | Q65: 46227 | R65: 496184 | S65: 483788 | T65: Закрыто и реализованно | U65: 102862 | V65: GAC S7 LMGNC3S82T1001936 | W65: Казань | X65: 2026 | Y65: FALSE | Z65: <a href="https://sberauto.bitrix24.ru/crm/deal/details/496184/"target="_blank">Ссылка</a>
A66: 729 | B66: 4545252 | C66: ONLINE ДИАЛОГ А | D66: =VLOOKUP(U66,Лист1!A:B,2,0) -> 1649021206 | E66: 2000000 | F66: 40000 | I66: 26/07/01-01 | J66: 46204 | K66: JETOUR | L66: X70PLUS | M66: Новое | N66: EC37CUGD3SC001034 | O66: 2000000 | P66: 40000 | Q66: 46226 | R66: 495578 | S66: 483382 | T66: Закрыто и реализованно | U66: 102862 | V66: JETOUR X70PLUS EC37CUGD3SC001034 | W66: Казань | X66: 2026 | Y66: FALSE | Z66: <a href="https://sberauto.bitrix24.ru/crm/deal/details/495578/"target="_blank">Ссылка</a>
A67: 731 | B67: 4906359 | C67: ONLINE ДИАЛОГ А | D67: =VLOOKUP(U67,Лист1!A:B,2,0) -> 1649021206 | E67: 5800000 | F67: 116000 | I67: 26/07/22-01 | J67: 46225 | K67: Gac | L67: S7 | M67: Новое | N67: LMGNC3S87T1001849 | O67: 5800000 | P67: 116000 | Q67: 46226 | R67: 495546 | S67: 483360 | T67: Закрыто и реализованно | U67: 102862 | V67: Gac S7 LMGNC3S87T1001849 | W67: Казань | X67: 2026 | Y67: FALSE | Z67: <a href="https://sberauto.bitrix24.ru/crm/deal/details/495546/"target="_blank">Ссылка</a>
... A82: 1188 | B82: 3887446 | C82: ONLINE Автодин (ООО "АВТОДИН-КАМА") | D82: =VLOOKUP(U82,Лист1!A:B,2,0) -> 1650129620 | E82: 2509990 | F82: 50199.8 | I82: 3131 | J82: 46208 | K82: BELGEE | L82: x50+ | M82: Новое | N82: Y4K8622Z5TB922154 | O82: 2509990 | P82: 50199.8 | Q82: 46213 | R82: 483880 | S82: 475186 | T82: Закрыто и реализованно | U82: 97080 | V82: BELGEE x50+ Y4K8622Z5TB922154 | W82: Москва | X82: 2026 | Y82: FALSE | Z82: <a href="https://sberauto.bitrix24.ru/crm/deal/details/483880/"target="_blank">Ссылка</a>
A83: 97 | B83: 4961200 | C83: Online ГК Диалог \ ООО "Управляющая компания Диалог" | D83: =VLOOKUP(U83,Лист1!A:B,2,0) -> 1650207558 | E83: 2300000 | F83: =E83*1.5% -> 34500 | G83: =E83*2% -> 46000 | I83: 30/07/26-3 | J83: 46233 | K83: JETOUR | L83: X70 PLUS | M83: Новое | N83: EC37LUSM9TC006523 | O83: 2300000 | Q83: 46233 | R83: 503088 | S83: 489108 | T83: Закрыто и реализованно | U83: 108224 | V83: JETOUR X70 PLUS EC37LUSM9TC006523 | W83: Набережные Челны | X83: 2026 | Y83: FALSE | Z83: <a href="https://sberauto.bitrix24.ru/crm/deal/details/503088/"target="_blank">Ссылка</a>
A84: 196 | B84: 4951944 | C84: Online ГК Диалог \ ООО "Управляющая компания Диалог" | D84: =VLOOKUP(U84,Лист1!A:B,2,0) -> 1650207558 | E84: 2300000 | F84: =E84*1.5% -> 34500 | G84: =E84*2% -> 46000 | I84: 26/07/29-03 | J84: 46232 | K84: Jetour | L84: X70+ | M84: Новое | N84: EC37LUSMXTC006501 | O84: 2300000 | P84: 46000 | Q84: 46233 | R84: 502140 | S84: 488366 | T84: Закрыто и реализованно | U84: 108224 | V84: Jetour X70+ EC37LUSMXTC006501 | W84: Набережные Челны | X84: 2026 | Y84: FALSE | Z84: <a href="https://sberauto.bitrix24.ru/crm/deal/details/502140/"target="_blank">Ссылка</a>
A85: 205 | B85: 4283385 | C85: Online ГК Диалог \ ООО "Управляющая компания Диалог" | D85: =VLOOKUP(U85,Лист1!A:B,2,0) -> 1650207558 | E85: 1970000 | F85: =E85*1.5% -> 29550 | G85: =E85*2% -> 39400 | I85: 26/07/26-03 | J85: 46229 | K85: Jetour | L85: Dashing | M85: Новое | N85: EC3DCUFD6TC010672 | O85: 1970000 | P85: 39400 | Q85: 46233 | R85: 502096 | S85: 485700 | T85: Закрыто и реализованно | U85: 108224 | V85: Jetour Dashing EC3DCUFD6TC010672 | W85: Набережные Челны | X85: 2026 | Y85: FALSE | Z85: <a href="https://sberauto.bitrix24.ru/crm/deal/details/502096/"target="_blank">Ссылка</a>
A86: 226 | B86: 4950393 | C86: Online ГК Диалог \ ООО "Управляющая компания Диалог" | D86: =VLOOKUP(U86,Лист1!A:B,2,0) -> 1650207558 | E86: 2280000 | F86: =E86*1.5% -> 34200 | G86: =E86*2% -> 45600 | I86: 29/07/26-44 | J86: 46232 | K86: Jetour | L86: X70+ | M86: Новое | N86: EC37LUSM7TC006696 | O86: 2280000 | P86: 45600 | Q86: 46233 | R86: 501520 | S86: 487878 | T86: Закрыто и реализованно | U86: 108224 | V86: Jetour X70+ EC37LUSM7TC006696 | W86: Казань | X86: 2026 | Y86: FALSE | Z86: <a href="https://sberauto.bitrix24.ru/crm/deal/details/501520/"target="_blank">Ссылка</a>
A87: 292 | B87: 1354247 | C87: Online ГК Диалог \ ООО "Управляющая компания Диалог" | D87: =VLOOKUP(U87,Лист1!A:B,2,0) -> 1650207558 | E87: 2130000 | F87: =E87*1.5% -> 31950 | G87: =E87*2% -> 42600 | I87: 26/07/09-001 | J87: 46212 | K87: Jetour | L87: X70+ | M87: Новое | N87: EC37CUSM4SC004628 | O87: 2130000 | P87: 42600 | Q87: 46232 | R87: 500940 | S87: 487440 | T87: Закрыто и реализованно | U87: 108224 | V87: Jetour X70+ EC37CUSM4SC004628 | W87: Набережные Челны | X87: 2026 | Y87: FALSE | Z87: <a href="https://sberauto.bitrix24.ru/crm/deal/details/500940/"target="_blank">Ссылка</a>
A88: 346 | B88: 4937596 | C88: Online ГК Диалог \ ООО "Управляющая компания Диалог" | D88: =VLOOKUP(U88,Лист1!A:B,2,0) -> 1650207558 | E88: 2250000 | F88: =E88*1.5% -> 33750 | G88: =E88*2% -> 45000 | I88: 26/07/27-04 | J88: 46230 | K88: JETOUR | L88: X70+ | M88: Новое | N88: EC37CUSM4SC004564 | O88: 2250000 | P88: 45000 | Q88: 46231 | R88: 500064 | S88: 486788 | T88: Закрыто и реализованно | U88: 108224 | V88: JETOUR X70PLUS EC37CUSM4SC004564 | X88: 2026 | Y88: TRUE | Z88: <a href="https://sberauto.bitrix24.ru/crm/deal/details/500064/"target="_blank">Ссылка</a>
A89: 416 | B89: 4930258 | C89: Online ГК Диалог \ ООО "Управляющая компания Диалог" | D89: =VLOOKUP(U89,Лист1!A:B,2,0) -> 1650207558 | E89: 2220000 | F89: =E89*1.5% -> 33300 | G89: =E89*2% -> 44400 | I89: 26/7/26-04 | J89: 46229 | K89: JETOUR | L89: X70PLUS | M89: Новое | N89: EC37CUSM5SC004444 | O89: 2220000 | P89: 44400 | Q89: 46229 | R89: 498596 | S89: 485674 | T89: Закрыто и реализованно | U89: 108224 | V89: JETOUR X70PLUS EC37CUSM5SC004444 | W89: Набережные Челны | X89: 2026 | Y89: FALSE | Z89: <a href="https://sberauto.bitrix24.ru/crm/deal/details/498596/"target="_blank">Ссылка</a>
A90: 460 | B90: 4925924 | C90: Online ГК Диалог \ ООО "Управляющая компания Диалог" | D90: =VLOOKUP(U90,Лист1!A:B,2,0) -> 1650207558 | E90: 2349000 | F90: =E90*1.5% -> 35235 | G90: =E90*2% -> 46980 | I90: 26/07/25-03 | J90: 46228 | K90: JETOUR | L90: DASHING | M90: Новое | N90: EC3DLUFD9TC012867 | O90: 2349000 | P90: 46980 | Q90: 46229 | R90: 497956 | S90: 485128 | T90: Закрыто и реализованно | U90: 108224 | V90: JETOUR DASHING EC3DLUFD9TC012867 | W90: Набережные Челны | X90: 2026 | Y90: FALSE | Z90: <a href="https://sberauto.bitrix24.ru/crm/deal/details/497956/"target="_blank">Ссылка</a>
A91: 561 | B91: 4920534 | C91: Online ГК Диалог \ ООО "Управляющая компания Диалог" | D91: =VLOOKUP(U91,Лист1!A:B,2,0) -> 1650207558 | E91: 2339000 | F91: =E91*1.5% -> 35085 | G91: =E91*2% -> 46780 | I91: 26/07/24-03 | J91: 46227 | K91: JETOUR | L91: DASHING | M91: Новое | N91: EC3DLUFD5TC015037 | O91: 2339000 | P91: 46780 | Q91: 46227 | R91: 496976 | S91: 484360 | T91: Закрыто и реализованно | U91: 108224 | V91: JETOUR DASHING EC3DLUFD5TC015037 | W91: Казань | X91: 2026 | Y91: FALSE | Z91: <a href="https://sberauto.bitrix24.ru/crm/deal/details/496976/"target="_blank">Ссылка</a>
A92: 840 | B92: 4889594 | C92: Online ГК Диалог \ ООО "Управляющая компания Диалог" | D92: =VLOOKUP(U92,Лист1!A:B,2,0) -> 1650207558 | E92: 2270000 | F92: =E92*1.5% -> 34050 | G92: =E92*2% -> 45400 | I92: 26/07/17-01 | J92: 46220 | K92: JETOUR | L92: X70Plus | M92: Новое | N92: EC37LUSM3TC006436 | O92: 2270000 | P92: 45400 | Q92: 46224 | R92: 493772 | S92: 482080 | T92: Закрыто и реализованно | U92: 108224 | V92: JETOUR X70PLUS EC37LUSM3TC006436 | W92: Казань | X92: 2026 | Y92: FALSE | Z92: <a href="https://sberauto.bitrix24.ru/crm/deal/details/493772/"target="_blank">Ссылка</a>
A93: 910 | B93: 4880325 | C93: Online ГК Диалог \ ООО "Управляющая компания Диалог" | D93: =VLOOKUP(U93,Лист1!A:B,2,0) -> 1650207558 | E93: 2200000 | F93: =E93*1.5% -> 33000 | G93: =E93*2% -> 44000 | I93: 17/07/2026-11 | J93: 46220 | K93: JETOUR | L93: X70PLUS | M93: Новое | N93: EC37LUSM2TC006489 | O93: 2200000 | P93: 44000 | Q93: 46224 | R93: 490696 | S93: 479990 | T93: Закрыто и реализованно | U93: 108224 | V93: JETOUR X70PLUS EC37LUSM2TC006489 | W93: Набережные Челны | X93: 2026 | Y93: FALSE | Z93: <a href="https://sberauto.bitrix24.ru/crm/deal/details/490696/"target="_blank">Ссылка</a>
A94: 1021 | B94: 4805851 | C94: Online ГК Диалог \ ООО "Управляющая компания Диалог" | D94: =VLOOKUP(U94,Лист1!A:B,2,0) -> 1650207558 | E94: 2050000 | F94: =E94*1.5% -> 30750 | G94: =E94*2% -> 41000 | I94: 26/07/10-03 | J94: 46213 | K94: JETOUR | L94: DASHING | M94: Новое | N94: EC3DCUFD6SC008290 | O94: 2050000 | P94: 41000 | Q94: 46217 | R94: 488052 | S94: 472378 | T94: Закрыто и реализованно | U94: 108224 | V94: JETOUR DASHING EC3DCUFD6SC008290 | W94: Казань | X94: 2026 | Y94: FALSE | Z94: <a href="https://sberauto.bitrix24.ru/crm/deal/details/488052/"target="_blank">Ссылка</a>
A95: 1037 | B95: 4858550 | C95: Online ГК Диалог \ ООО "Управляющая компания Диалог" | D95: =VLOOKUP(U95,Лист1!A:B,2,0) -> 1650207558 | E95: 2070000 | F95: =E95*1.5% -> 31050 | G95: =E95*2% -> 41400 | I95: 26/07/14-01 | J95: 46217 | K95: JETOUR | L95: DASHING | M95: Новое | N95: EC3DCUFD9TC014036 | O95: 2070000 | P95: 41400 | Q95: 46219 | R95: 487826 | S95: 477938 | T95: Закрыто и реализованно | U95: 108224 | V95: JETOUR DASHING EC3DCUFD9TC014036 | W95: Казань | X95: 2026 | Y95: FALSE | Z95: <a href="https://sberauto.bitrix24.ru/crm/deal/details/487826/"target="_blank">Ссылка</a>
A96: 1110 | B96: 4842790 | C96: Online ГК Диалог \ ООО "Управляющая компания Диалог" | D96: =VLOOKUP(U96,Лист1!A:B,2,0) -> 1650207558 | E96: 1970000 | F96: =E96*1.5% -> 29550 | G96: =E96*2% -> 39400 | I96: 26/07/11-05 | J96: 46214 | K96: JETOUR | L96: DASHING | M96: Новое | N96: EC3DCUFD7TC010549 | O96: 1970000 | P96: 39400 | Q96: 46215 | R96: 485566 | S96: 476354 | T96: Закрыто и реализованно | U96: 108224 | V96: JETOUR DASHING EC3DCUFD7TC010549 | W96: Набережные Челны | X96: 2026 | Y96: FALSE | Z96: <a href="https://sberauto.bitrix24.ru/crm/deal/details/485566/"target="_blank">Ссылка</a>
A97: 1128 | B97: 4841275 | C97: Online ГК Диалог \ ООО "Управляющая компания Диалог" | D97: =VLOOKUP(U97,Лист1!A:B,2,0) -> 1650207558 | E97: 1970000 | F97: =E97*1.5% -> 29550 | G97: =E97*2% -> 39400 | I97: 26/07/11-03 | J97: 46214 | K97: JETOUR | L97: DASHING | M97: Новое | N97: EC3DCUFD6TC010641 | O97: 1970000 | P97: 39400 | Q97: 46215 | R97: 485316 | S97: 476158 | T97: Закрыто и реализованно | U97: 108224 | V97: JETOUR DASHING EC3DCUFD6TC010641 | W97: Набережные Челны | X97: 2026 | Y97: FALSE | Z97: <a href="https://sberauto.bitrix24.ru/crm/deal/details/485316/"target="_blank">Ссылка</a>
A98: 1177 | B98: 4834870 | C98: Online ГК Диалог \ ООО "Управляющая компания Диалог" | D98: =VLOOKUP(U98,Лист1!A:B,2,0) -> 1650207558 | E98: 6119100 | F98: =E98*1.5% -> 91786.5 | G98: =E98*2% -> 122382 | I98: 26/07/10-01 | J98: 46213 | K98: GAC | L98: S9 | M98: Новое | N98: LMGJF3S82T1000372 | O98: 6119100 | P98: 122382 | Q98: 46214 | R98: 484218 | S98: 475394 | T98: Закрыто и реализованно | U98: 108224 | V98: GAC S9 LMGJF3S82T1000372 | W98: Казань | X98: 2026 | Y98: FALSE | Z98: <a href="https://sberauto.bitrix24.ru/crm/deal/details/484218/"target="_blank">Ссылка</a>
A99: 1294 | B99: 4708726 | C99: Online ГК Диалог \ ООО "Управляющая компания Диалог" | D99: =VLOOKUP(U99,Лист1!A:B,2,0) -> 1650207558 | E99: 2270000 | F99: =E99*1.5% -> 34050 | G99: =E99*2% -> 45400 | I99: 26/07/06-03 | J99: 46209 | K99: JETOUR | L99: X70PLUS | M99: Новое | N99: EC37LUSM7TC005225 | O99: 2270000 | P99: 45400 | Q99: 46210 | R99: 481308 | S99: 473404 | T99: Закрыто и реализованно | U99: 108224 | V99: JETOUR X70PLUS EC37LUSM7TC005225 | W99: Набережные Челны | X99: 2026 | Y99: FALSE | Z99: <a href="https://sberauto.bitrix24.ru/crm/deal/details/481308/"target="_blank">Ссылка</a>
A100: 1398 | B100: 4804885 | C100: Online ГК Диалог \ ООО "Управляющая компания Диалог" | D100: =VLOOKUP(U100,Лист1!A:B,2,0) -> 1650207558 | E100: 1970000 | F100: =E100*1.5% -> 29550 | G100: =E100*2% -> 39400 | I100: 26/07/03-04 | J100: 46206 | K100: JETOUR | L100: DASHING | M100: Новое | N100: EC3DCUFD4TC010301 | O100: 1970000 | P100: 39400 | Q100: 46207 | R100: 478474 | S100: 471318 | T100: Закрыто и реализованно | U100: 108224 | V100: JETOUR DASHING EC3DCUFD4TC010301 | W100: Казань | X100: 2026 | Y100: FALSE | Z100: <a href="https://sberauto.bitrix24.ru/crm/deal/details/478474/"target="_blank">Ссылка</a>
... A102: 1481 | B102: 4771259 | C102: Online ГК Диалог \ ООО "Управляющая компания Диалог" | D102: =VLOOKUP(U102,Лист1!A:B,2,0) -> 1650207558 | E102: 1925000 | F102: =E102*1.5% -> 28875 | G102: =E102*2% -> 38500 | I102: 26/07/02-03 | J102: 46205 | K102: JETOUR | L102: DASHING | M102: Новое | N102: EC3DCUFD9TC014179 | O102: 1925000 | P102: 38500 | Q102: 46209 | R102: 471830 | S102: 466076 | T102: Закрыто и реализованно | U102: 108224 | V102: JETOUR DASHING EC3DCUFD9TC014179 | W102: Казань | X102: 2026 | Y102: FALSE | Z102: <a href="https://sberauto.bitrix24.ru/crm/deal/details/471830/"target="_blank">Ссылка</a>
A103: 271 | B103: 4940115 | C103: ONLINE Апельсин (ООО "АПЕЛЬСИН-ЧЕЛНЫ") | D103: =VLOOKUP(U103,Лист1!A:B,2,0) -> 1650392340 | E103: 2588750 | F103: 51775 | I103: АЧ00002386 | J103: 46231 | K103: SOLARIS | L103: HC | M103: Новое | N103: Z}4PB}I4BSR070155 | O103: 2588750 | P103: 51775 | Q103: 46232 | R103: 501092 | S103: 487554 | T103: Закрыто и реализованно | U103: 84628 | V103: SOLARIS HC Z94PB814BSR070155 | W103: Набережные челны | X103: 2025 | Y103: FALSE | Z103: <a href="https://sberauto.bitrix24.ru/crm/deal/details/501092/"target="_blank">Ссылка</a>
A104: 490 | B104: 3474768 | C104: ONLINE Апельсин (ООО "АПЕЛЬСИН-ЧЕЛНЫ") | D104: =VLOOKUP(U104,Лист1!A:B,2,0) -> 1650392340 | E104: 820000 | F104: 12300 | I104: Ач00002358 | J104: 46228 | K104: Lada | L104: Granta | M104: Новое | N104: XTA219040T1251540 | O104: 820000 | P104: 12300 | Q104: 46228 | R104: 497722 | S104: 484946 | T104: Закрыто и реализованно | U104: 84628 | V104: Lada Granta XTA219040T1251540 | W104: Набережные Челны | X104: 2026 | Y104: FALSE | Z104: <a href="https://sberauto.bitrix24.ru/crm/deal/details/497722/"target="_blank">Ссылка</a>
A105: 525 | B105: 4603880 | C105: ONLINE Апельсин (ООО "АПЕЛЬСИН-ЧЕЛНЫ") | D105: =VLOOKUP(U105,Лист1!A:B,2,0) -> 1650392340 | E105: 3173000 | F105: 63460 | I105: Ач00002355 | J105: 46228 | K105: Solaris | L105: НС | M105: Новое | N105: Z94PC815DSR070764 | O105: 3173000 | P105: 63460 | Q105: 46228 | R105: 497472 | S105: 484746 | T105: Закрыто и реализованно | U105: 84628 | V105: Solaris НС Z94PC815DSR070764 | W105: Набережные Челны | X105: 2025 | Y105: FALSE | Z105: <a href="https://sberauto.bitrix24.ru/crm/deal/details/497472/"target="_blank">Ссылка</a>
A106: 717 | B106: 4906758 | C106: ONLINE Апельсин (ООО "АПЕЛЬСИН-ЧЕЛНЫ") | D106: =VLOOKUP(U106,Лист1!A:B,2,0) -> 1650392340 | E106: 2646100 | F106: 52922 | I106: Ач00002311 | J106: 46225 | K106: SOLARIS | L106: KRX | M106: Новое | N106: Z94C351BBSR200011 | O106: 2646100 | P106: 52922 | Q106: 46227 | R106: 495708 | S106: 483484 | T106: Закрыто и реализованно | U106: 84628 | V106: Solaris KRX Z94C351BBSR200011 | W106: Набережные челны | X106: 2026 | Y106: FALSE | Z106: <a href="https://sberauto.bitrix24.ru/crm/deal/details/495708/"target="_blank">Ссылка</a>
A107: 1397 | B107: 2775934 | C107: ONLINE Апельсин (ООО "АПЕЛЬСИН-ЧЕЛНЫ") | D107: =VLOOKUP(U107,Лист1!A:B,2,0) -> 1650392340 | E107: 2244000 | F107: 44880 | I107: ЧА00001056 | J107: 46211 | K107: JETOUR | L107: X70 Plus | M107: Новое | N107: EC37LUSM6SC003853 | O107: 2244000 | P107: 44880 | Q107: 46212 | R107: 478512 | S107: 471350 | T107: Закрыто и реализованно | U107: 84628 | V107: Jetour X70 Plus EC37LUSM6SC003853 | W107: Набережные Челны | X107: 2026 | Y107: FALSE | Z107: <a href="https://sberauto.bitrix24.ru/crm/deal/details/478512/"target="_blank">Ссылка</a>
A108: 28 | B108: 1107012 | C108: ГК Апельсин \ Челны-Авто Чери | D108: =VLOOKUP(U108,Лист1!A:B,2,0) -> 1650402781 | E108: 2244000 | F108: 33660 | I108: ЧА00001215 | J108: 46234 | K108: JETOUR | L108: X70 + | M108: Новое | N108: EC37LUSM1SC003887 | O108: 2244000 | P108: 33660 | Q108: 46234 | R108: 505286 | S108: 489394 | T108: Закрыто и реализованно | U108: 95202 | V108: Jetour X70 Plus EC37LUSM1SC003887 | W108: Набережные Челны | X108: 2025 | Y108: FALSE | Z108: <a href="https://sberauto.bitrix24.ru/crm/deal/details/505286/"target="_blank">Ссылка</a>
A109: 261 | B109: 4948229 | C109: ГК Апельсин \ Челны-Авто Чери | D109: =VLOOKUP(U109,Лист1!A:B,2,0) -> 1650402781 | E109: 2270000 | F109: 34050 | I109: ЧА00001186 | J109: 46232 | K109: Jetour | L109: X70+ | M109: Новое | N109: EC37LUSM5TC007278 | O109: 2270000 | P109: 34050 | Q109: 46233 | R109: 501216 | S109: 487648 | T109: Закрыто и реализованно | U109: 95202 | V109: Jetour X70+ EC37LUSM5TC007278 | W109: Набережные Челны | X109: 2026 | Y109: FALSE | Z109: <a href="https://sberauto.bitrix24.ru/crm/deal/details/501216/"target="_blank">Ссылка</a>
A110: 317 | B110: 4941697 | C110: ГК Апельсин \ Челны-Авто Чери | D110: =VLOOKUP(U110,Лист1!A:B,2,0) -> 1650402781 | E110: 1970000 | F110: 29550 | I110: ЧА00001182 | J110: 46231 | K110: JETOUR | L110: DASHING | M110: Новое | N110: EC3DCUFD8TC011743 | O110: 1970000 | P110: 29550 | Q110: 46231 | R110: 500412 | S110: 487060 | T110: Закрыто и реализованно | U110: 95202 | V110: JETOUR DASHING EC3DCUFD8TC011743 | X110: 2026 | Y110: TRUE | Z110: <a href="https://sberauto.bitrix24.ru/crm/deal/details/500412/"target="_blank">Ссылка</a>
A111: 386 | B111: 4907997 | C111: ГК Апельсин \ Челны-Авто Чери | D111: =VLOOKUP(U111,Лист1!A:B,2,0) -> 1650402781 | E111: 1970000 | F111: 39400 | I111: ЧА00001149 | J111: 46225 | K111: JETOUR | L111: DASHING | M111: Новое | N111: EC3DCUFD6TC013961 | O111: 1970000 | P111: 39400 | Q111: 46230 | R111: 499384 | S111: 486322 | T111: Закрыто и реализованно | U111: 95202 | V111: JETOUR Dashing EC3DCUFD6ТС013961 | W111: Набережные Челны | X111: 2026 | Y111: FALSE | Z111: <a href="https://sberauto.bitrix24.ru/crm/deal/details/499384/"target="_blank">Ссылка</a>
A112: 679 | B112: 4895155 | C112: ГК Апельсин \ Челны-Авто Чери | D112: =VLOOKUP(U112,Лист1!A:B,2,0) -> 1650402781 | E112: 2270000 | F112: 45400 | I112: ЧА00001142 | J112: 46224 | K112: JETOUR | L112: X70 PLUS | M112: Новое | N112: EC37LUSM7TC007234 | O112: 2270000 | P112: 45400 | Q112: 46227 | R112: 496364 | S112: 481680 | T112: Закрыто и реализованно | U112: 95202 | V112: JETOUR X70 PLUS EC37LUSM7TC007234 | W112: Набережные Челны | X112: 2026 | Y112: FALSE | Z112: <a href="https://sberauto.bitrix24.ru/crm/deal/details/496364/"target="_blank">Ссылка</a>
A113: 868 | B113: 4866728 | C113: ГК Апельсин \ Челны-Авто Чери | D113: =VLOOKUP(U113,Лист1!A:B,2,0) -> 1650402781 | E113: 2270000 | F113: 45400 | I113: ЧА00001146 | J113: 46224 | K113: Jetour | L113: X70 PLUS | M113: Новое | N113: EC37LUSM5TC007314 | O113: 2270000 | P113: 45400 | Q113: 46227 | R113: 492938 | S113: 479668 | T113: Закрыто и реализованно | U113: 95202 | V113: Jetour X70 PLUS EC37LUSM5TC007314 | W113: Набережные Челны | X113: 2026 | Y113: FALSE | Z113: <a href="https://sberauto.bitrix24.ru/crm/deal/details/492938/"target="_blank">Ссылка</a>
A114: 1097 | B114: 4845769 | C114: ГК Апельсин \ Челны-Авто Чери | D114: =VLOOKUP(U114,Лист1!A:B,2,0) -> 1650402781 | E114: 1970000 | F114: 39400 | I114: ЧА00001078 | J114: 46215 | K114: JETOUR | L114: DASHING | M114: Новое | N114: EC3DCUFD0TC014880 | O114: 1970000 | P114: 39400 | Q114: 46215 | R114: 485982 | S114: 476632 | T114: Закрыто и реализованно | U114: 95202 | V114: JETOUR DASHING EC3DCUFD0TC014880 | W114: Набережные Челны | X114: 2026 | Y114: FALSE | Z114: <a href="https://sberauto.bitrix24.ru/crm/deal/details/485982/"target="_blank">Ссылка</a>
A115: 1375 | B115: 4807319 | C115: ГК Апельсин \ Челны-Авто Чери | D115: =VLOOKUP(U115,Лист1!A:B,2,0) -> 1650402781 | E115: 2270000 | F115: 45400 | I115: ЧА00001033 | J115: 46207 | K115: JETOUR | L115: X70+ | M115: Новое | N115: EC37LUSMXTC004988 | O115: 2270000 | P115: 45400 | Q115: 46230 | R115: 478868 | S115: 471656 | T115: Закрыто и реализованно | U115: 95202 | V115: Jetour X70+ EC37LUSMXTC004988 | W115: Набережные Челны | X115: 2026 | Y115: FALSE | Z115: <a href="https://sberauto.bitrix24.ru/crm/deal/details/478868/"target="_blank">Ссылка</a>
A116: 7 | B116: 4953329 | C116: ООО "КАН АВТО-5" ONLINE | D116: =VLOOKUP(U116,Лист1!A:B,2,0) -> 1657190695 | E116: 2130000 | F116: 42600 | H116: в личке битрикса отчет от 24 года | I116: ААК5-001158 | J116: 46234 | K116: Jetour | L116: Х70+ | M116: Новое | N116: EC37LUSM2SC001792 | O116: 2130000 | P116: 42600 | Q116: 46234 | R116: 506084 | S116: 491342 | T116: Закрыто и реализованно | U116: 112940 | V116: Jetour Х70+ EC37LUSM2SC001792 | W116: Казань | X116: 2026 | Y116: FALSE | Z116: <a href="https://sberauto.bitrix24.ru/crm/deal/details/506084/"target="_blank">Ссылка</a>
A117: 225 | B117: 4710405 | C117: ООО "КАН АВТО-5" ONLINE | D117: =VLOOKUP(U117,Лист1!A:B,2,0) -> 1657190695 | E117: 4245000 | F117: 84900 | H117: в личке битрикса отчет от 24 года | I117: ААК5-001141 | J117: 46232 | K117: Jetour | L117: Т2 | M117: Новое | N117: EC3TDUMA5T0004395 | O117: 4245000 | P117: 84900 | Q117: 46232 | R117: 501540 | S117: 484538 | T117: Закрыто и реализованно | U117: 112940 | V117: Jetour Т2 EC3TDUMA5T0004395 | W117: Казань | X117: 2026 | Y117: FALSE | Z117: <a href="https://sberauto.bitrix24.ru/crm/deal/details/501540/"target="_blank">Ссылка</a>
A118: 404 | B118: 38951 | C118: ООО "КАН АВТО-5" ONLINE | D118: =VLOOKUP(U118,Лист1!A:B,2,0) -> 1657190695 | E118: 2130000 | F118: 21300 | H118: в личке битрикса отчет от 24 года | I118: ААК5-001127 | J118: 46229 | K118: Jetour | L118: X70 PLUS | M118: Новое | N118: EC37CUSM2SC003073 | O118: 2130000 | P118: 21300 | Q118: 46229 | R118: 498670 | S118: 416200 | T118: Закрыто и реализованно | U118: 112940 | V118: Jetour X70 PLUS EC37CUSM2SC003073 | W118: Казань | X118: 2026 | Y118: FALSE | Z118: <a href="https://sberauto.bitrix24.ru/crm/deal/details/498670/"target="_blank">Ссылка</a>
...

Sheet Лист1
A1: ID | B1: Реквизит (Россия): ИНН
A2: 113168 | B2: 5257188836
A4: 113166
A5: 113164
A6: 113162
A7: 113160 | B7: 7810684545
A8: 113158 | B8: 5001048893
A10: 113156 | B10: 5001048893
A12: 113154
A13: 113152
A14: 113150
A15: 113148
A16: 113146 | B16: 276971419
A17: 113144
A18: 113142
A19: 113140
A20: 113138 | B20: 3664048710
A21: 113134
A22: 113132
A23: 113130 | B23: 7804540104
A24: 113128 | B24: 7729520988
A25: 113126
A26: 113124
A27: 113122
A28: 113120
A29: 113118 | B29: 5403342038
A31: 113116 | B31: 6732074435
A32: 113114 | B32: 7814721879
A33: 113112
A34: 113110 | B34: 7730653453
A35: 113108
A36: 113106 | B36: 7814824190
A37: 113104
A38: 113102
A39: 113100
A40: 113098
A41: 113096
A42: 113094
A43: 113092
A44: 113090 | B44: 7814367593
A45: 113088 | B45: 7606128876
A46: 113086
A47: 113084
A48: 113082
A49: 113080
A50: 113078 | B50: 245961925
A51: 113076
A52: 113074
A53: 113072 | B53: 2902058926
A54: 113070
A55: 113068 | B55: 6382027669
A57: 113066
A58: 113064
A59: 113062 | B59: 6320011130
A60: 113060
A61: 113058
A62: 113056
A63: 113054
A64: 113052 | B64: 5403342038
A66: 113050 | B66: 6314034107
A67: 113048
A68: 113046
A69: 113044
A70: 113042
A71: 113040 | B71: 5403342038
A73: 113038
A74: 113036
A75: 113034
A76: 113032
A77: 113030
A78: 113028 | B78: 5403342038
A80: 113026
A81: 113024
A82: 113022
A83: 113020
A84: 113018
A85: 113016
A86: 113014
A87: 113012
A88: 113010
A89: 113008
A90: 113006
A91: 113004
A92: 113002 | B92: 6027177158
A93: 113000
A94: 112998
A95: 112996 | B95: 5262004523
A96: 112994
A97: 112992
A98: 112990
A99: 112988 | B99: 3257014272
A100: 112986
A101: 112984 | B101: 7714709349
A103: 112982
A104: 112980
A105: 112978
A106: 112974
A107: 112972
A108: 112970
A109: 112968
...
